Workbook
Name Ccy: Inputs!$C$7
Name circ: Inputs!$C$10
Name CoName: Inputs!$C$4
Name g: Presentation!$R$17
Name IQ_CH: 110000
Name IQ_CQ: 5000
Name IQ_CY: 10000
Name IQ_DAILY: 500000
Name IQ_FH: 100000
Name IQ_FQ: 500
Name IQ_FY: 1000
Name IQ_LTM: 2000
Name IQ_MONTH: 15000
Name IQ_NTM: 6000
Name IQ_WEEK: 50000
Name IQ_YTD: 3000
Name OpCase: [1]DCF!$E$98
Name ScenarioCAPEX: Assumptions!$P$3
Name ScenarioCOGS: Assumptions!$L$3
Name ScenarioREV: Assumptions!$D$3
Name TTS: #REF!
Name Units: Inputs!$C$8
Name wacc: 'DCF Model'!$C$27

Sheet Inputs
A1: =CoName -> Alphabet Inc.
A2: Advanced DCF + COMPS + SOTP Analysis
B4: Company name | C4: Alphabet Inc. | E4: Diluted s/o | F4: =28196/2.31 -> 12206.061
B5: Current Stock Price | C5: {=_FV(A14,"Price")} -> 253.3 | E5: Mkt Cap | F5: =F4*C5 -> 3091795.2
B6: Latest BS date | C6: 45690 | E6: Cash | F6: =21036+74112 -> 95148
B7: Currency | C7: USD | E7: Debt | F7: =23607 -> 23607
B8: Units | C8: m | E8: EV | F8: =F5-F6+F7 -> 3020254.2
B9: Analyst name | C9: Alan Chen
B10: Circular switch | C10: 0
B11: TURN THIS ON AFTER TURNING ON ITERATIONS, NOT BEFORE
A13: Other temp stuff
A14: #VALUE!
F16: Terminal Mult. | G16: Gordon Growth | J16: Football Field | K16: Sum-of-the-Parts
E17: Implied Price | F17: ='DCF Model'!G18 -> 232.50422 | G17: ='DCF Model'!C18 -> 225.46716 | I17: Implied Price | J17: =COMPS!G45 -> 244.03902 | K17: 243.7
E18: Difference | F18: =F17/$C$5-1 -> -0.08209939 | G18: =G17/$C$5-1 -> -0.10988093 | I18: Difference | J18: =J17/$C$5-1 -> -0.036561328 | K18: =K17/$C$5-1 -> -0.037899724
E21: Weighted average
E22: Price | F22: =AVERAGE(F17:G17,J17:K17) -> 236.4276
E23: Difference | F23: =AVERAGE(F18:G18,J18:K18) -> -0.066610343

Sheet Revenues
A1: =CoName -> Alphabet Inc. | C1: Hist. | D1: Hist. | E1: Hist. | F1: Hist. | G1: Hist. | H1: Hist. | I1: Hist. | J1: Hist. | K1: Hist. | L1: Hist. | M1: Hist. | N1: Hist. | O1: Hist. | P1: Hist. | Q1: Proj. | R1: Proj. | S1: Proj. | T1: Proj. | U1: Proj. | V1: Proj. | W1: Proj. | X1: Proj. | Y1: Proj. | Z1: Proj.
A2: Revenue Breakdown (Segment) | C2: 2021 | D2: 2022 | E2: Q123 | F2: Q223 | G2: Q323 | H2: Q423 | I2: 2023 | J2: Q124 | K2: Q224 | L2: Q324 | M2: Q424 | N2: 2024 | O2: Q125 | P2: Q225 | Q2: Q325E | R2: Q425E | S2: 2025E | T2: 2025E | U2: 2027E | V2: 2028E | W2: 2029E | X2: 2030E | Y2: 2031E | Z2: 2032E | AA2: CAGR
B3: Google Search & Other | C3: 148951 | D3: 162450 | E3: 40359 | F3: 42628 | G3: 44026 | H3: =I3-SUM(E3:G3) -> 48020 | I3: 175033 | J3: 46156 | K3: 48509 | L3: 49385 | M3: =N3-SUM(J3:L3) -> 54034 | N3: 198084 | O3: 50702 | P3: 54190 | Q3: =L3*(1+Q4) -> 55311.2 | R3: =M3*(1+R4) -> 62139.1 | S3: =SUM(O3:R3) -> 222342.3 | T3: =S3*(1+T4) -> 249571.39 | U3: =T3*(1+U4) -> 280135.07 | V3: =U3*(1+V4) -> 314441.73 | W3: =V3*(1+W4) -> 352949.75 | X3: =W3*(1+X4) -> 396173.64 | Y3: =X3*(1+Y4) -> 444690.93 | Z3: =Y3*(1+Z4) -> 499149.88 | AA3: =(Z3/S3)^(1/8)-1 -> 0.10637183
B4: Y/Y% | C4: =C3/104062-1 -> 0.43136784 | D4: =D3/C3-1 -> 0.090627119 | I4: =I3/D3-1 -> 0.077457679 | J4: =J3/E3-1 -> 0.14363587 | K4: =K3/F3-1 -> 0.13796096 | L4: =L3/G3-1 -> 0.12172353 | M4: =M3/H3-1 -> 0.12523948 | N4: =N3/I3-1 -> 0.13169517 | O4: =O3/J3-1 -> 0.09849207 | P4: =P3/K3-1 -> 0.11711229 | Q4: 0.12 | R4: 0.15 | S4: =S3/N3-1 -> 0.12246471 | T4: =S4 -> 0.12246471 | U4: =T4 -> 0.12246471 | V4: =U4 -> 0.12246471 | W4: =V4 -> 0.12246471 | X4: =W4 -> 0.12246471 | Y4: =X4 -> 0.12246471 | Z4: =Y4 -> 0.12246471
B5: Q/Q% | J5: =J3/H3-1 -> -0.03881716 | K5: =K3/J3-1 -> 0.050979288 | L5: =L3/K3-1 -> 0.018058505 | M5: =M3/L3-1 -> 0.094137896 | O5: =O3/M3-1 -> -0.061664878 | P5: =P3/O3-1 -> 0.06879413 | Q5: =Q3/P3-1 -> 0.020690164 | R5: =R3/Q3-1 -> 0.12344516
B6: Youtube ads | C6: 28845 | D6: 29243 | E6: 6693 | F6: 7665 | G6: 7952 | H6: =I6-SUM(E6:G6) -> 9200 | I6: 31510 | J6: 8090 | K6: 8663 | L6: 8921 | M6: =N6-SUM(J6:L6) -> 10473 | N6: 36147 | O6: 8927 | P6: 9796 | Q6: =L6*(1+Q7) -> 9983.4722 | R6: =M6*(1+R7) -> 11720.312 | S6: =SUM(O6:R6) -> 40426.784 | T6: =S6*(1+T7) -> 45213.293 | U6: =T6*(1+U7) -> 50566.521 | V6: =U6*(1+V7) -> 56553.569 | W6: =V6*(1+W7) -> 63249.479 | X6: =W6*(1+X7) -> 70738.182 | Y6: =X6*(1+Y7) -> 79113.543 | Z6: =Y6*(1+Z7) -> 88480.541 | AA6: =(Z6/S6)^(1/8)-1 -> 0.10286492
B7: Y/Y% | C7: =C6/19772-1 -> 0.45888125 | D7: =D6/C6-1 -> 0.013797885 | I7: =I6/D6-1 -> 0.077522826 | J7: =J6/E6-1 -> 0.20872553 | K7: =K6/F6-1 -> 0.13020222 | L7: =L6/G6-1 -> 0.12185614 | M7: =M6/H6-1 -> 0.13836957 | N7: =N6/I6-1 -> 0.14715963 | O7: =O6/J6-1 -> 0.10346106 | P7: =P6/K6-1 -> 0.1307861 | Q7: =AVERAGE(D7:P7) -> 0.11909788 | R7: =Q7 -> 0.11909788 | S7: =S6/N6-1 -> 0.11839943 | T7: =S7 -> 0.11839943 | U7: =T7 -> 0.11839943 | V7: =U7 -> 0.11839943 | W7: =V7 -> 0.11839943 | X7: =W7 -> 0.11839943 | Y7: =X7 -> 0.11839943 | Z7: =Y7 -> 0.11839943
B8: Q/Q% | J8: =J6/H6-1 -> -0.12065217 | K8: =K6/J6-1 -> 0.070828183 | L8: =L6/K6-1 -> 0.029781831 | M8: =M6/L6-1 -> 0.17397153 | O8: =O6/M6-1 -> -0.14761768 | P8: =P6/O6-1 -> 0.097345133 | Q8: =Q6/P6-1 -> 0.019137631 | R8: =R6/Q6-1 -> 0.17397153
B9: Google Network | C9: 31701 | D9: 32780 | E9: 7496 | F9: 7850 | G9: 7669 | H9: =I9-SUM(E9:G9) -> 8297 | I9: 31312 | J9: 7413 | K9: 7444 | L9: 7548 | M9: =N9-SUM(J9:L9) -> 7954 | N9: 30359 | O9: 7256 | P9: 7354 | Q9: =L9*(1+Q10) -> 7623.48 | R9: =M9*(1+R10) -> 8033.54 | S9: =SUM(O9:R9) -> 30267.02 | T9: =S9*(1+T10) -> 30175.319 | U9: =T9*(1+U10) -> 30083.895 | V9: =U9*(1+V10) -> 29992.749 | W9: =V9*(1+W10) -> 29901.878 | X9: =W9*(1+X10) -> 29811.283 | Y9: =X9*(1+Y10) -> 29720.963 | Z9: =Y9*(1+Z10) -> 29630.916 | AA9: =(Z9/S9)^(1/8)-1 -> -0.0026515286
B10: Y/Y% | C10: =C9/23090-1 -> 0.37293201 | D10: =D9/C9-1 -> 0.034036781 | I10: =I9/D9-1 -> -0.044783405 | J10: =J9/E9-1 -> -0.011072572 | K10: =K9/F9-1 -> -0.051719745 | L10: =L9/G9-1 -> -0.015777807 | M10: =M9/H9-1 -> -0.041340243 | N10: =N9/I9-1 -> -0.030435616 | O10: =O9/J9-1 -> -0.02117901 | P10: =P9/K9-1 -> -0.012090274 | Q10: 0.01 | R10: =Q10 -> 0.01 | S10: =S9/N9-1 -> -0.0030297441 | T10: =S10 -> -0.0030297441 | U10: =T10 -> -0.0030297441 | V10: =U10 -> -0.0030297441 | W10: =V10 -> -0.0030297441 | X10: =W10 -> -0.0030297441 | Y10: =X10 -> -0.0030297441 | Z10: =Y10 -> -0.0030297441
B11: Q/Q% | J11: =J9/H9-1 -> -0.10654453 | K11: =K9/J9-1 -> 0.0041818427 | L11: =L9/K9-1 -> 0.013970983 | M11: =M9/L9-1 -> 0.053789083 | O11: =O9/M9-1 -> -0.087754589 | P11: =P9/O9-1 -> 0.013506064 | Q11: =Q9/P9-1 -> 0.036644003 | R11: =R9/Q9-1 -> 0.053789083
A12: * | B12: Total advertising revenue | C12: =SUM(C9,C6,C3) -> 209497 | D12: =SUM(D9,D6,D3) -> 224473 | E12: =SUM(E9,E6,E3) -> 54548 | F12: =SUM(F9,F6,F3) -> 58143 | G12: =SUM(G9,G6,G3) -> 59647 | H12: =SUM(H9,H6,H3) -> 65517 | I12: =SUM(I9,I6,I3) -> 237855 | J12: =SUM(J9,J6,J3) -> 61659 | ... Z12: =SUM(Z9,Z6,Z3) -> 617261.34 | AA12: =(Z12/S12)^(1/8)-1 -> 0.097598469
B13: Y/Y% | C13: =C12/146924-1 -> 0.42588685 | D13: =D12/C12-1 -> 0.071485511 | I13: =I12/D12-1 -> 0.059615188 | J13: =J12/E12-1 -> 0.13036225 | K13: =K12/F12-1 -> 0.11132896 | L13: =L12/G12-1 -> 0.10406223 | M13: =M12/H12-1 -> 0.10598776 | N13: =N12/I12-1 -> 0.11240041 | O13: =O12/J12-1 -> 0.084756483 | P13: =P12/K12-1 -> 0.10406091 | ... S13: =S12/N12-1 -> 0.10751013 | T13: =T12/S12-1 -> 0.10894184 | U13: =U12/T12-1 -> 0.11024585 | V13: =V12/U12-1 -> 0.11143065 | W13: =W12/V12-1 -> 0.11250474 | X13: =X12/W12-1 -> 0.11347651 | Y13: =Y12/X12-1 -> 0.11435411 | Z13: =Z12/Y12-1 -> 0.11514538
B14: Q/Q% | J14: =J12/H12-1 -> -0.05888548 | K14: =K12/J12-1 -> 0.047957314 | L14: =L12/K12-1 -> 0.019159341 | M14: =M12/L12-1 -> 0.100328 | O14: =O12/M12-1 -> -0.07695174 | P14: =P12/O12-1 -> 0.066606863 | Q14: =Q12/P12-1 -> 0.022121562 | R14: =R12/Q12-1 -> 0.12308046
B15: % Of total revenue | C15: =C12/C26 -> 0.81314796 | D15: =D12/D26 -> 0.79365074 | E15: =E12/E26 -> 0.78164675 | F15: =F12/F26 -> 0.77935499 | G15: =G12/G26 -> 0.77773721 | H15: =H12/H26 -> 0.75908053 | I15: =I12/I26 -> 0.77377893 | J15: =J12/J26 -> 0.76557941 | ... P15: =P12/P26 -> 0.73982661 | Q15: =Q12/$Q$26 -> 0.71443565 | R15: =R12/R26 -> 0.72427828 | S15: =S12/S26 -> 0.72931864 | T15: =T12/T26 -> 0.699046 | U15: =U12/U26 -> 0.66501423 | V15: =V12/V26 -> 0.63048507 | W15: =W12/W26 -> 0.59846468 | X15: =X12/X26 -> 0.56855609 | Y15: =Y12/Y26 -> 0.54045899 | Z15: =Z12/Z26 -> 0.51395294
B16: Subscriptions, platforms, devices | C16: 28032 | D16: 29055 | E16: 7413 | F16: 8142 | G16: 8339 | H16: =I16-SUM(E16:G16) -> 10794 | I16: 34688 | J16: 8739 | K16: 9312 | L16: 10656 | M16: =N16-SUM(J16:L16) -> 11633 | N16: 40340 | O16: 10379 | P16: 11203 | Q16: =L16*(1+Q17) -> 12787.2 | R16: =M16*(1+R17) -> 13959.6 | S16: =SUM(O16:R16) -> 48328.8 | T16: =S16*(1+T17) -> 57899.675 | U16: =T16*(1+U17) -> 69365.935 | V16: =U16*(1+V17) -> 83102.936 | W16: =V16*(1+W17) -> 99560.366 | X16: =W16*(1+X17) -> 119276.97 | Y16: =X16*(1+Y17) -> 142898.19 | Z16: =Y16*(1+Z17) -> 171197.27 | AA16: =(Z16/S16)^(1/8)-1 -> 0.17128169
B17: Y/Y% | C17: =C16/21711-1 -> 0.29114274 | D17: =D16/C16-1 -> 0.036494007 | I17: =I16/D16-1 -> 0.19387369 | J17: =J16/E16-1 -> 0.17887495 | K17: =K16/F16-1 -> 0.14369934 | L17: =L16/G16-1 -> 0.27785106 | M17: =M16/H16-1 -> 0.077728368 | N17: =N16/I16-1 -> 0.16293819 | O17: =O16/J16-1 -> 0.18766449 | P17: =P16/K16-1 -> 0.20307131 | Q17: 0.2 | R17: =Q17 -> 0.2 | S17: =S16/N16-1 -> 0.19803669 | T17: =S17 -> 0.19803669 | U17: =T17 -> 0.19803669 | V17: =U17 -> 0.19803669 | W17: =V17 -> 0.19803669 | X17: =W17 -> 0.19803669 | Y17: =X17 -> 0.19803669 | Z17: =Y17 -> 0.19803669
B18: Q/Q% | J18: =J16/H16-1 -> -0.19038355 | K18: =K16/J16-1 -> 0.065568143 | L18: =L16/K16-1 -> 0.1443299 | M18: =M16/L16-1 -> 0.091685435 | O18: =O16/M16-1 -> -0.10779679 | P18: =P16/O16-1 -> 0.079391078 | Q18: =Q16/P16-1 -> 0.14140855 | R18: =R16/Q16-1 -> 0.091685435
B19: Google Cloud | C19: 19206 | D19: 26280 | E19: 7453 | F19: 8031 | G19: 8411 | H19: =I19-SUM(E19:G19) -> 9193 | I19: 33088 | J19: 9574 | K19: 10347 | L19: 11353 | M19: =N19-SUM(J19:L19) -> 11955 | N19: 43229 | O19: 12260 | P19: 13624 | Q19: =L19*(1+Q20) -> 15894.2 | R19: =M19*(1+R20) -> 16737 | S19: =SUM(O19:R19) -> 58515.2 | T19: =S19*(1+T20) -> 80109.477 | U19: =T19*(1+U20) -> 110342.77 | V19: =U19*(1+V20) -> 149733.96 | W19: =V19*(1+W20) -> 197417.44 | X19: =W19*(1+X20) -> 255159.56 | Y19: =X19*(1+Y20) -> 325076.24 | Z19: =Y19*(1+Z20) -> 409680.14 | AA19: =(Z19/S19)^(1/8)-1 -> 0.2754018 | AB19: Don't change the values, these adjustments are already in the 3 different operating revenues scenario
B20: Y/Y% | C20: =C19/13059-1 -> 0.47070986 | D20: =D19/C19-1 -> 0.3683224 | I20: =I19/D19-1 -> 0.25905632 | J20: =J19/E19-1 -> 0.28458339 | K20: =K19/F19-1 -> 0.28838252 | L20: =L19/G19-1 -> 0.34978005 | M20: =M19/H19-1 -> 0.30044599 | N20: =N19/I19-1 -> 0.30648574 | O20: =O19/J19-1 -> 0.28055149 | P20: =P19/K19-1 -> 0.31671016 | Q20: 0.4 | R20: 0.4 | S20: =S19/N19-1 -> 0.35360985 | T20: =AC21 -> 0.36903705 | U20: =AD21 -> 0.37739967 | V20: =AE21 -> 0.35698936 | W20: =AF21 -> 0.31845467 | X20: =AG21 -> 0.29248746 | Y20: =AH21 -> 0.27401157 | Z20: =AI21 -> 0.26025864 | AB20: 1
B21: Q/Q% | J21: =J19/H19-1 -> 0.041444577 | K21: =K19/J19-1 -> 0.080739503 | L21: =L19/K19-1 -> 0.097226249 | M21: =M19/L19-1 -> 0.053025632 | O21: =O19/M19-1 -> 0.025512338 | P21: =P19/O19-1 -> 0.11125612 | Q21: =Q19/P19-1 -> 0.16663241 | R21: =R19/Q19-1 -> 0.053025632 | AB21: Case Scenario | AC21: =CHOOSE($AB$20,AC23,AC24) -> 0.36903705 | AD21: =CHOOSE($AB$20,AD23,AD24) -> 0.37739967 | AE21: =CHOOSE($AB$20,AE23,AE24) -> 0.35698936 | AF21: =CHOOSE($AB$20,AF23,AF24) -> 0.31845467 | AG21: =CHOOSE($AB$20,AG23,AG24) -> 0.29248746 | AH21: =CHOOSE($AB$20,AH23,AH24) -> 0.27401157 | AI21: =CHOOSE($AB$20,AI23,AI24) -> 0.26025864
B22: Other bets | C22: 753 | D22: 1068 | E22: 288 | F22: 285 | G22: 297 | H22: =I22-SUM(E22:G22) -> 657 | I22: 1527 | J22: 495 | K22: 365 | L22: 388 | M22: =N22-SUM(J22:L22) -> 400 | N22: 1648 | O22: 450 | P22: 373 | Q22: =L22*(1+Q23) -> 464.43721 | R22: =M22*(1+R23) -> 478.80125 | S22: =SUM(O22:R22) -> 1766.2385 | T22: =S22*(1+T23) -> 1892.9601 | U22: =T22*(1+U23) -> 2028.7737 | V22: =U22*(1+V23) -> 2174.3313 | W22: =V22*(1+W23) -> 2330.3323 | X22: =W22*(1+X23) -> 2497.5258 | Y22: =X22*(1+Y23) -> 2676.7149 | Z22: =Y22*(1+Z23) -> 2868.7602 | AA22: =(Z22/S22)^(1/8)-1 -> 0.062504098
B23: Y/Y% | C23: =C22/657-1 -> 0.14611872 | D23: =D22/C22-1 -> 0.41832669 | I23: =I22/D22-1 -> 0.42977528 | J23: =J22/E22-1 -> 0.71875 | K23: =K22/F22-1 -> 0.28070175 | L23: =L22/G22-1 -> 0.30639731 | M23: =M22/H22-1 -> -0.39117199 | N23: =N22/I22-1 -> 0.079240341 | O23: =O22/J22-1 -> -0.090909091 | P23: =P22/K22-1 -> 0.021917808 | Q23: =AVERAGE(D23:P23) -> 0.19700312 | R23: =Q23 -> 0.19700312 | S23: =S22/N22-1 -> 0.071746638 | T23: =S23 -> 0.071746638 | U23: =T23 -> 0.071746638 | V23: =U23 -> 0.071746638 | W23: =V23 -> 0.071746638 | X23: =W23 -> 0.071746638 | Y23: =X23 -> 0.071746638 | Z23: =Y23 -> 0.071746638 | AB23: Efficient Capex | AC23: 0.36903705 | AD23: 0.37739967 | AE23: 0.35698936 | AF23: 0.31845467 | AG23: 0.29248746 | AH23: 0.27401157 | AI23: 0.26025864
B24: Q/Q% | J24: =J22/H22-1 -> -0.24657534 | K24: =K22/J22-1 -> -0.26262626 | L24: =L22/K22-1 -> 0.063013699 | M24: =M22/L22-1 -> 0.030927835 | O24: =O22/M22-1 -> 0.125 | P24: =P22/O22-1 -> -0.17111111 | Q24: =Q22/P22-1 -> 0.24513998 | R24: =R22/Q22-1 -> 0.030927835 | AB24: Inefficient Capex | AC24: 0.24792249 | AD24: 0.29969234 | AE24: 0.29969234 | AF24: 0.29969234 | AG24: 0.29969234 | AH24: 0.29969234 | AI24: 0.29969234
B25: Hedging gains (losses) | C25: 149 | D25: 1960 | E25: 84 | F25: 3 | G25: -1 | H25: =I25-SUM(E25:G25) -> 150 | I25: 236 | J25: 72 | K25: 102 | L25: 17 | M25: =N25-SUM(J25:L25) -> 20 | N25: 211 | O25: 260 | P25: -112 | S25: =SUM(O25:R25) -> 148
A26: * | B26: Total Net Revenue (by segments) | C26: =SUM(C25,C22,C19,C16,C12) -> 257637 | D26: =SUM(D25,D22,D19,D16,D12) -> 282836 | E26: =SUM(E25,E22,E19,E16,E12) -> 69786 | F26: =SUM(F25,F22,F19,F16,F12) -> 74604 | G26: =SUM(G25,G22,G19,G16,G12) -> 76693 | H26: =SUM(H25,H22,H19,H16,H12) -> 86311 | I26: =SUM(I25,I22,I19,I16,I12) -> 307394 | J26: =SUM(J25,J22,J19,J16,J12) -> 80539 | ... Z26: =SUM(Z25,Z22,Z19,Z16,Z12) -> 1201007.5 | AA26: =(Z26/S26)^(1/8)-1 -> 0.14668132
B27: Y/Y% | C27: =C26/182527-1 -> 0.41150076 | D27: =D26/C26-1 -> 0.097808156 | I27: =I26/D26-1 -> 0.086827702 | J27: =J26/E26-1 -> 0.15408535 | K27: =K26/F26-1 -> 0.13589084 | L27: =L26/G26-1 -> 0.15092642 | M27: =M26/H26-1 -> 0.11769068 | N27: =N26/I26-1 -> 0.13866243 | O27: =O26/J26-1 -> 0.12037646 | P27: =P26/K26-1 -> 0.13790092 | ... S27: =S26/N26-1 -> 0.1479248 | T27: =T26/S26-1 -> 0.15696529 | U27: =U26/T26-1 -> 0.16706213 | V27: =V26/U26-1 -> 0.17229927 | W27: =W26/V26-1 -> 0.17202844 | X27: =X26/W26-1 -> 0.17205035 | Y27: =Y26/X26-1 -> 0.17228658 | Z27: =Z26/Y26-1 -> 0.17265668
A29: Revenue Breakdown (Region) | C29: 2021 | D29: 2022 | E29: Q123 | F29: Q223 | G29: Q323 | H29: Q423 | I29: 2023 | J29: Q124 | K29: Q224 | L29: Q324 | M29: Q424 | N29: 2024 | O29: Q125 | P29: Q225 | Q29: Q325E | R29: Q425E | S29: 2025E | T29: 2025E | U29: 2027E | V29: 2028E | W29: 2029E | X29: 2030E | Y29: 2031E | Z29: 2032E
B30: United States | C30: 117854 | D30: 134814 | E30: 32864 | F30: 35073 | G30: 36354 | H30: 41995 | I30: 146286 | J30: 38737 | K30: 41196 | L30: 43139 | M30: 47375 | N30: 170447 | O30: 43964 | P30: 46063 | Q30: =Q33*Q26 -> 48755.274 | R30: =R33*R26 -> 54011.984 | S30: =S33*$S$26 -> 191934.43 | T30: =T33*$T$26 -> 222061.47 | U30: =U33*$U$26 -> 259159.53 | AA30: =(Z30/S30)^(1/8)-1 -> -1
B31: Y/Y% | C31: =C30/85014-1 -> 0.38628932 | D31: =D30/C30-1 -> 0.14390687 | I31: =I30/D30-1 -> 0.08509502 | J31: =J30/E30-1 -> 0.17870618 | K31: =K30/F30-1 -> 0.17457874 | L31: =L30/G30-1 -> 0.18663696 | M31: =M30/H30-1 -> 0.12811049 | N31: =N30/I30-1 -> 0.16516276 | O31: =O30/J30-1 -> 0.13493559 | P31: =P30/O30-1 -> 0.047743608 | Q31: =Q30/L30-1 -> 0.13019017 | R31: =R30/M30-1 -> 0.14009464
B32: Q/Q% | J32: =J30/H30-1 -> -0.077580664 | K32: =K30/J30-1 -> 0.063479361 | L32: =L30/K30-1 -> 0.047164773 | M32: =M30/L30-1 -> 0.098194209 | O32: =O30/M30-1 -> -0.072 | P32: =P30/O30-1 -> 0.047743608 | Q32: =Q30/P30-1 -> 0.058447644 | R32: =R30/Q30-1 -> 0.10781828
B33: % Of total revenue | C33: =C30/$C$54 -> 0.45744206 | D33: =D30/$D$54 -> 0.47665078 | I33: =I30/$I$54 -> 0.47589088 | J33: =J30/J54 -> 0.48097195 | K33: =K30/$K$54 -> 0.48613438 | L33: =L30/$L$54 -> 0.48872751 | M33: =M30/$M$54 -> 0.4910904 | N33: =N30/$N$54 -> 0.48696638 | O33: =O30/$O$54 -> 0.48722211 | P33: =P30/$P$54 -> 0.4776932 | Q33: =P33 -> 0.4776932 | R33: =Q33 -> 0.4776932 | S33: =R33 -> 0.4776932 | T33: =S33 -> 0.4776932 | U33: =T33 -> 0.4776932 | V33: =U33 -> 0.4776932 | W33: =V33 -> 0.4776932 | X33: =W33 -> 0.4776932 | ... Z33: =Y33 -> 0.4776932
B34: Other Americas | C34: 14404 | D34: 16976 | E34: 4080 | F34: 4511 | G34: 4553 | H34: 5176 | I34: 18320 | J34: 4653 | K34: 4938 | L34: 5093 | M34: 5734 | N34: 20418 | O34: 5233 | P34: 5735 | Q34: =Q37*$Q$26 -> 6070.1972 | R34: =R37*$R$26 -> 6724.6755 | S34: =S37*$S$26 -> 23896.488 | T34: =T37*$T$26 -> 27647.407 | U34: =U37*$U$26 -> 32266.242 | AA34: =(Z34/S34)^(1/8)-1 -> -1
B35: Y/Y% | C35: =C34/9417-1 -> 0.52957417 | D35: =D34/C34-1 -> 0.17856151 | I35: =I34/D34-1 -> 0.079170594 | J35: =J34/E34-1 -> 0.14044118 | K35: =K34/F34-1 -> 0.094657504 | L35: =L34/G34-1 -> 0.11860312 | M35: =M34/H34-1 -> 0.10780526 | N35: =N34/I34-1 -> 0.11451965 | O35: =O34/J34-1 -> 0.12465076 | P35: =P34/O34-1 -> 0.095929677 | Q35: =Q34/L34-1 -> 0.19187065 | R35: =R34/M34-1 -> 0.17277214
B36: Q/Q% | J36: =J34/H34-1 -> -0.10104328 | K36: =K34/J34-1 -> 0.061250806 | L36: =L34/K34-1 -> 0.031389226 | M36: =M34/L34-1 -> 0.12585902 | O36: =O34/M34-1 -> -0.087373561 | P36: =P34/O34-1 -> 0.095929677 | Q36: =Q34/P34-1 -> 0.058447644 | R36: =R34/Q34-1 -> 0.10781828
B37: % Of total revenue | C37: =C34/$C$54 -> 0.055908119 | D37: =D34/$D$54 -> 0.060020648 | I37: =I34/$I$54 -> 0.05959778 | J37: =J34/J54 -> 0.057773253 | K37: =K34/$K$54 -> 0.058270987 | L37: =L34/$L$54 -> 0.057699279 | M37: =M34/$M$54 -> 0.059438783 | N37: =N34/$N$54 -> 0.058334143 | O37: =O34/$O$54 -> 0.057993661 | P37: =P34/$P$54 -> 0.059474427 | Q37: =P37 -> 0.059474427 | R37: =Q37 -> 0.059474427 | S37: =R37 -> 0.059474427 | T37: =S37 -> 0.059474427 | U37: =T37 -> 0.059474427 | V37: =U37 -> 0.059474427 | W37: =V37 -> 0.059474427 | X37: =W37 -> 0.059474427 | ... Z37: =Y37 -> 0.059474427
A38: * | B38: Total Americas Revenue | C38: =SUM(C34,C30) -> 132258 | D38: =SUM(D34,D30) -> 151790 | E38: =SUM(E34,E30) -> 36944 | F38: =SUM(F34,F30) -> 39584 | G38: =SUM(G34,G30) -> 40907 | H38: =SUM(H34,H30) -> 47171 | I38: =SUM(I34,I30) -> 164606 | J38: =SUM(J34,J30) -> 43390 | ... P38: =SUM(P34,P30) -> 51798 | Q38: =Q41*Q26 -> 54825.471 | R38: =R41*$R$26 -> 60736.659 | S38: =SUM(S34,S30) -> 215830.91 | T38: =SUM(T34,T30) -> 249708.88 | U38: =SUM(U34,U30) -> 291425.77 | V38: =SUM(V34,V30) -> 0 | W38: =SUM(W34,W30) -> 0 | X38: =SUM(X34,X30) -> 0 | Y38: =SUM(Y34,Y30) -> 0 | Z38: =SUM(Z34,Z30) -> 0 | AA38: =(Z38/S38)^(1/8)-1 -> -1
B39: Y/Y% | C39: =C38/(85014+9417)-1 -> 0.4005782 | D39: =D38/C38-1 -> 0.14768105 | I39: =I38/D38-1 -> 0.08443244 | J39: =J38/E38-1 -> 0.17448029 | K39: =K38/F38-1 -> 0.1654709 | L39: =L38/G38-1 -> 0.17906471 | M39: =M38/H38-1 -> 0.12588243 | N39: =N38/I38-1 -> 0.15952638 | O39: =O38/J38-1 -> 0.13383268 | P39: =P38/O38-1 -> 0.052869077 | Q39: =Q38/L38-1 -> 0.13670325 | R39: =R38/M38-1 -> 0.14362272
B40: Q/Q% | J40: =J38/H38-1 -> -0.08015518 | K40: =K38/J38-1 -> 0.063240378 | L40: =L38/K38-1 -> 0.045476221 | M40: =M38/L38-1 -> 0.10111544 | O40: =O38/M38-1 -> -0.073659832 | P40: =P38/O38-1 -> 0.052869077 | Q40: =Q38/P38-1 -> 0.058447644 | R40: =R38/Q38-1 -> 0.10781828
B41: % Of total revenue | C41: =C38/$C$54 -> 0.51335018 | D41: =D38/$D$54 -> 0.53667143 | I41: =I38/$I$54 -> 0.53548866 | J41: =J38/J54 -> 0.5387452 | K41: =K38/$K$54 -> 0.54440537 | L41: =L38/$L$54 -> 0.54642679 | M41: =M38/$M$54 -> 0.55052919 | N41: =N38/$N$54 -> 0.54530053 | O41: =O38/$O$54 -> 0.54521577 | P41: =P38/$P$54 -> 0.53716763 | Q41: =P41 -> 0.53716763 | R41: =Q41 -> 0.53716763 | S41: =R41 -> 0.53716763 | T41: =S41 -> 0.53716763 | U41: =T41 -> 0.53716763 | V41: =U41 -> 0.53716763 | W41: =V41 -> 0.53716763 | X41: =W41 -> 0.53716763 | ... Z41: =Y41 -> 0.53716763
B42: EMEA | C42: 79107 | D42: 82062 | E42: 21078 | F42: 22289 | G42: 22661 | H42: 25010 | I42: 91038 | J42: 23788 | K42: 24683 | L42: 25472 | M42: 28184 | N42: 102127 | O42: 25923 | P42: 28262 | Q42: =Q45*$Q$26 -> 29913.847 | R42: =R45*$R$26 -> 33139.107 | S42: =S45*$S$26 -> 117761.56 | T42: =T45*$T$26 -> 136246.04 | U42: =U45*$U$26 -> 159007.59 | AA42: =(Z42/S42)^(1/8)-1 -> -1
B43: Y/Y% | C43: =C42/55370-1 -> 0.42869785 | D43: =D42/C42-1 -> 0.037354469 | I43: =I42/D42-1 -> 0.10938071 | J43: =J42/E42-1 -> 0.12857007 | K43: =K42/F42-1 -> 0.10740724 | L43: =L42/G42-1 -> 0.12404572 | M43: =M42/H42-1 -> 0.12690924 | N43: =N42/I42-1 -> 0.12180628 | O43: =O42/J42-1 -> 0.089751135 | P43: =P42/O42-1 -> 0.090228754 | Q43: =Q42/L42-1 -> 0.17438157 | R43: =R42/M42-1 -> 0.17581276
B44: Q/Q% | J44: =J42/H42-1 -> -0.048860456 | K44: =K42/J42-1 -> 0.037624012 | L44: =L42/K42-1 -> 0.03196532 | M44: =M42/L42-1 -> 0.10646985 | O44: =O42/M42-1 -> -0.080222821 | P44: =P42/O42-1 -> 0.090228754 | Q44: =Q42/P42-1 -> 0.058447644 | R44: =R42/Q42-1 -> 0.10781828
B45: % Of total revenue | C45: =C42/$C$54 -> 0.30704829 | D45: =D42/$D$54 -> 0.29013987 | I45: =I42/$I$54 -> 0.29616063 | J45: =J42/$J$54 -> 0.29536001 | K45: =K42/$K$54 -> 0.29127233 | L45: =L42/$L$54 -> 0.2885757 | M45: =M42/$M$54 -> 0.29215603 | N45: =N42/$N$54 -> 0.29177642 | O45: =O42/$O$54 -> 0.28728639 | P45: =P42/$P$54 -> 0.29308914 | Q45: =P45 -> 0.29308914 | R45: =Q45 -> 0.29308914 | S45: =R45 -> 0.29308914 | T45: =S45 -> 0.29308914 | U45: =T45 -> 0.29308914 | V45: =U45 -> 0.29308914 | W45: =V45 -> 0.29308914 | X45: =W45 -> 0.29308914 | ... Z45: =Y45 -> 0.29308914
B46: APAC | C46: 46123 | D46: 47024 | E46: 11681 | F46: 12728 | G46: 13126 | H46: 13979 | I46: 51514 | J46: 13289 | K46: 13823 | L46: 14547 | M46: 15156 | N46: 56815 | O46: 14854 | P46: 16480 | Q46: =Q49*$Q$26 -> 17443.217 | R46: =R49*$R$26 -> 19323.915 | S46: =S49*$S$26 -> 68668.548 | T46: =T49*$T$26 -> 79447.127 | U46: =U49*$U$26 -> 92719.734 | AA46: =(Z46/S46)^(1/8)-1 -> -1
B47: Y/Y% | C47: =C46/32550-1 -> 0.41698925 | D47: =D46/C46-1 -> 0.019534722 | I47: =I46/D46-1 -> 0.095483158 | J47: =J46/E46-1 -> 0.13765945 | K47: =K46/F46-1 -> 0.086030798 | L47: =L46/G46-1 -> 0.10825842 | M47: =M46/H46-1 -> 0.084197725 | N47: =N46/I46-1 -> 0.10290406 | O47: =O46/J46-1 -> 0.11776657 | P47: =P46/O46-1 -> 0.10946546 | Q47: =Q46/L46-1 -> 0.19909378 | R47: =R46/M46-1 -> 0.27500098
B48: Q/Q% | J48: =J46/H46-1 -> -0.049359754 | K48: =K46/J46-1 -> 0.040183611 | L48: =L46/K46-1 -> 0.052376474 | M48: =M46/L46-1 -> 0.041864302 | O48: =O46/M46-1 -> -0.019926102 | P48: =P46/O46-1 -> 0.10946546 | Q48: =Q46/P46-1 -> 0.058447644 | R48: =R46/Q46-1 -> 0.10781828
B49: % Of total revenue | C49: =C46/$C$54 -> 0.1790232 | D49: =D46/$D$54 -> 0.16625889 | I49: =I46/$I$54 -> 0.16758297 | J49: =J46/$J$54 -> 0.16500081 | K49: =K46/$K$54 -> 0.16311864 | L49: =L46/$L$54 -> 0.16480491 | M49: =M46/$M$54 -> 0.15710746 | N49: =N46/$N$54 -> 0.16232022 | O49: =O46/$O$54 -> 0.16461644 | P49: =P46/$P$54 -> 0.17090472 | Q49: =P49 -> 0.17090472 | R49: =Q49 -> 0.17090472 | S49: =R49 -> 0.17090472 | T49: =S49 -> 0.17090472 | U49: =T49 -> 0.17090472 | V49: =U49 -> 0.17090472 | W49: =V49 -> 0.17090472 | X49: =W49 -> 0.17090472 | ... Z49: =Y49 -> 0.17090472
A50: * | B50: Total International Revenue | C50: =SUM(C46,C42) -> 125230 | D50: =SUM(D46,D42) -> 129086 | E50: =SUM(E46,E42) -> 32759 | F50: =SUM(F46,F42) -> 35017 | G50: =SUM(G46,G42) -> 35787 | H50: =SUM(H46,H42) -> 38989 | I50: =SUM(I46,I42) -> 142552 | J50: =SUM(J46,J42) -> 37077 | ... P50: =SUM(P46,P42) -> 44742 | Q50: =Q53*Q26 -> 47357.064 | R50: =SUM(R46,R42) -> 52463.022 | S50: =SUM(S46,S42) -> 186430.11 | T50: =T53*$T$26 -> 215693.16 | U50: =SUM(U46,U42) -> 251727.33 | V50: =SUM(V46,V42) -> 0 | W50: =SUM(W46,W42) -> 0 | X50: =SUM(X46,X42) -> 0 | Y50: =SUM(Y46,Y42) -> 0 | Z50: =SUM(Z46,Z42) -> 0 | AA50: =(Z50/S50)^(1/8)-1 -> -1
B51: Y/Y% | C51: =C50/(55370+32550)-1 -> 0.42436306 | D51: =D50/C50-1 -> 0.030791344 | I51: =I50/D50-1 -> 0.10431805 | J51: =J50/E50-1 -> 0.13181111 | K51: =K50/F50-1 -> 0.099637319 | L51: =L50/G50-1 -> 0.11825523 | M51: =M50/H50-1 -> 0.11159558 | N51: =N50/I50-1 -> 0.11497559 | O51: =O50/J50-1 -> 0.099792324 | P51: =P50/O50-1 -> 0.097236187 | Q51: =Q50/L50-1 -> 0.18336451 | R51: =R50/M50-1 -> 0.21049889
B52: Q/Q% | J52: =J50/H50-1 -> -0.049039473 | K52: =K50/J50-1 -> 0.038541414 | L52: =L50/K50-1 -> 0.039292578 | M52: =M50/L50-1 -> 0.082985582 | O52: =O50/M50-1 -> -0.059137056 | P52: =P50/O50-1 -> 0.097236187 | Q52: =Q50/P50-1 -> 0.058447644 | R52: =R50/Q50-1 -> 0.10781828
B53: % Of total revenue | C53: =C50/$C$54 -> 0.48607149 | D53: =D50/$D$54 -> 0.45639876 | I53: =I50/$I$54 -> 0.4637436 | J53: =J50/$J$54 -> 0.46036082 | K53: =K50/$K$54 -> 0.45439097 | L53: =L50/$L$54 -> 0.45338061 | M53: =M50/$M$54 -> 0.44926349 | N53: =N50/$N$54 -> 0.45409665 | O53: =O50/$O$54 -> 0.45190283 | P53: =P50/$P$54 -> 0.46399386 | Q53: =P53 -> 0.46399386 | R53: =Q53 -> 0.46399386 | S53: =R53 -> 0.46399386 | T53: =S53 -> 0.46399386 | U53: =T53 -> 0.46399386 | V53: =U53 -> 0.46399386 | W53: =V53 -> 0.46399386 | X53: =W53 -> 0.46399386 | ... Z53: =Y53 -> 0.46399386
A54: * | B54: Total Net Revenue (by segments) | C54: =SUM(C50,C38)+C25 -> 257637 | D54: =SUM(D50,D38)+D25 -> 282836 | E54: =SUM(E50,E38)+E25 -> 69787 | F54: =SUM(F50,F38)+F25 -> 74604 | G54: =SUM(G50,G38)+G25 -> 76693 | H54: =SUM(H50,H38)+H25 -> 86310 | I54: =SUM(I50,I38)+I25 -> 307394 | J54: =SUM(J50,J38)+J25 -> 80539 | ... P54: =SUM(P50,P38)+P25 -> 96428 | Q54: =Q26 -> 102063.99 | R54: =R26 -> 113068.35 | S54: =SUM(S50,S38)+S25 -> 402409.02 | T54: =SUM(T50,T38)+T25 -> 465402.04 | U54: =SUM(U50,U38)+U25 -> 543153.1 | V54: =SUM(V50,V38)+V25 -> 0 | W54: =SUM(W50,W38)+W25 -> 0 | X54: =SUM(X50,X38)+X25 -> 0 | Y54: =SUM(Y50,Y38)+Y25 -> 0 | Z54: =SUM(Z50,Z38)+Z25 -> 0 | AA54: =(Z54/S54)^1/8 -> 0
B55: Y/Y% | C55: =C54/182527-1 -> 0.41150076 | D55: =D54/C54-1 -> 0.097808156 | I55: =I54/D54-1 -> 0.086827702 | J55: =J54/E54-1 -> 0.15406881 | K55: =K54/F54-1 -> 0.13589084 | L55: =L54/G54-1 -> 0.15092642 | M55: =M54/H54-1 -> 0.11770363 | N55: =N54/I54-1 -> 0.13866243 | O55: =O54/J54-1 -> 0.12037646 | P55: =P54/O54-1 -> 0.068643748 | Q55: =Q54/L54-1 -> 0.15629661 | R55: =R54/M54-1 -> 0.1720693
O56: =O54/M54-1 -> -0.064632162 | P56: =P54/O54-1 -> 0.068643748 | Q56: =Q54/P54-1 -> 0.058447644 | R56: =R54/Q54-1 -> 0.10781828

Sheet Assumptions
A1: =CoName -> Alphabet Inc. | C1: Hist. | D1: Hist. | E1: Hist. | F1: Proj. | G1: Proj. | H1: Proj. | I1: Proj. | J1: Proj. | K1: Proj. | L1: Proj. | M1: Proj.
A2: * | B2: Income Statement | C2: 44926 | D2: 45291 | E2: 45657 | F2: 46022 | G2: 46387 | H2: 46752 | I2: 47118 | J2: 47483 | K2: 47848 | L2: 48213 | M2: 48579
B3: Operating Case | D3: 1 | O3: Capex Case | P3: 1
D4: Variance
B5: Street Case | D5: 0 | F5: 0.1479248 | G5: 0.13932681 | H5: 0.15141023 | I5: 0.15657367 | J5: 0.16189467 | K5: 0.16737261 | L5: 0.17300063 | M5: 0.17876527 | O5: Base Capex case | P5: 0.212 | Q5: =P5-0.015 -> 0.197 | R5: =Q5-0.015 -> 0.182 | S5: =R5-0.015 -> 0.167 | T5: =S5-0.015 -> 0.152 | U5: =T5-0.015 -> 0.137 | V5: =U5-0.015 -> 0.122 | W5: =V5-0.015 -> 0.107
B6: Optimistic Case | D6: 0.025 | F6: =Revenues!S27 -> 0.1479248 | G6: =Revenues!T27 -> 0.15696529 | H6: =Revenues!U27 -> 0.16706213 | I6: =Revenues!V27 -> 0.17229927 | J6: =Revenues!W27 -> 0.17202844 | K6: =Revenues!X27 -> 0.17205035 | L6: =Revenues!Y27 -> 0.17228658 | M6: =Revenues!Z27 -> 0.17265668 | O6: Pessimistic Capex case | P6: 0.212 | Q6: =P6-0.01 -> 0.202 | R6: =Q6-0.01 -> 0.192 | S6: =R6-0.01 -> 0.182 | T6: =S6-0.01 -> 0.172 | U6: =T6-0.01 -> 0.162 | V6: =U6-0.01 -> 0.152 | W6: =V6-0.01 -> 0.142
B7: Pessimistic Case | D7: -0.025 | F7: =F5+$D$7 -> 0.1229248 | G7: =G5+$D$7 -> 0.11432681 | H7: =H5+$D$7 -> 0.12641023 | I7: =I5+$D$7 -> 0.13157367 | J7: =J5+$D$7 -> 0.13689467 | K7: =K5+$D$7 -> 0.14237261 | L7: =L5+$D$7 -> 0.14800063 | M7: =M5+$D$7 -> 0.15376527
B9: Revenue Growth | C9: =Revenues!D27 -> 0.097808156 | D9: =Revenues!I27 -> 0.086827702 | E9: =Revenues!N27 -> 0.13866243 | F9: =CHOOSE(ScenarioREV,F5,F6,F7) -> 0.1479248 | G9: =CHOOSE(ScenarioREV,G5,G6,G7) -> 0.13932681 | H9: =CHOOSE(ScenarioREV,H5,H6,H7) -> 0.15141023 | I9: =CHOOSE(ScenarioREV,I5,I6,I7) -> 0.15657367 | J9: =CHOOSE(ScenarioREV,J5,J6,J7) -> 0.16189467 | K9: =CHOOSE(ScenarioREV,K5,K6,K7) -> 0.16737261 | L9: =CHOOSE(ScenarioREV,L5,L6,L7) -> 0.17300063 | M9: =CHOOSE(ScenarioREV,M5,M6,M7) -> 0.17876527
B10: COGS % of sales | C10: =IncState!C18/IncState!C17 -> 0.44620557 | D10: =IncState!D18/IncState!D17 -> 0.43374952 | E10: =IncState!E18/IncState!E17 -> 0.41799565 | F10: =E10 -> 0.41799565 | G10: =F10 -> 0.41799565 | H10: =G10 -> 0.41799565 | I10: =H10 -> 0.41799565 | J10: =I10 -> 0.41799565 | K10: =J10 -> 0.41799565 | L10: =K10 -> 0.41799565 | M10: =L10 -> 0.41799565
B11: R&D % of sales | C11: =IncState!C19/IncState!C17 -> 0.1396569 | D11: =IncState!D19/IncState!D17 -> 0.14778102 | E11: =IncState!E19/IncState!E17 -> 0.14092418 | F11: =E11 -> 0.14092418 | G11: =F11 -> 0.14092418 | H11: =G11 -> 0.14092418 | I11: =H11 -> 0.14092418 | J11: =I11 -> 0.14092418 | K11: =J11 -> 0.14092418 | L11: =K11 -> 0.14092418 | M11: =L11 -> 0.14092418
B12: SG&A % of sales | C12: =IncState!C20/IncState!C17 -> 0.14952481 | D12: =IncState!D20/IncState!D17 -> 0.14425135 | E12: =IncState!E20/IncState!E17 -> 0.1199824 | F12: =E12 -> 0.1199824 | G12: =F12 -> 0.1199824 | H12: =G12 -> 0.1199824 | I12: =H12 -> 0.1199824 | J12: =I12 -> 0.1199824 | K12: =J12 -> 0.1199824 | L12: =K12 -> 0.1199824 | M12: =L12 -> 0.1199824
B13: Amortization $ Amt | C13: 0 | D13: 0 | E13: 0 | F13: 0 | G13: 0 | H13: 0 | I13: 0 | J13: 0 | K13: 0 | L13: 0 | M13: 0
B14: Non recurring income / (expense) | C14: 0 | D14: 0 | E14: 0 | F14: -1400 | G14: 0 | H14: 0 | I14: 0 | J14: 0 | K14: 0 | L14: 0 | M14: 0
B15: Other Income / (expense) | C15: =IncState!C28 -> -5331 | D15: =IncState!D28 -> -2390 | E15: =IncState!E28 -> 3211 | F15: 0 | G15: 0 | H15: 0 | I15: 0 | J15: 0 | K15: 0 | L15: 0 | M15: 0
B16: Effective tax rate | C16: =IncState!C11 -> 0.15920817 | D16: =IncState!D11 -> 0.13950386 | E16: =IncState!E11 -> 0.16439511 | F16: =E16+0.016 -> 0.18039511 | G16: =F16 -> 0.18039511 | H16: =G16 -> 0.18039511 | I16: =H16 -> 0.18039511 | J16: =I16 -> 0.18039511 | K16: =J16 -> 0.18039511 | L16: =K16 -> 0.18039511 | M16: =L16 -> 0.18039511
B17: Dividend Payout Rate | C17: 0 | D17: 0 | E17: =IncState!E12 -> 0.073543219 | F17: =IncState!F12 -> 0.0854 | G17: =F17 -> 0.0854 | H17: =G17 -> 0.0854 | I17: =H17 -> 0.0854 | J17: =I17 -> 0.0854 | K17: =J17 -> 0.0854 | L17: =K17 -> 0.0854 | M17: =L17 -> 0.0854
B18: Basic WASO | C18: =IncState!C40 -> 13065.795 | D18: =IncState!D40 -> 12592.123 | E18: =IncState!E40 -> 12314.637 | F18: =E18 -> 12314.637 | G18: =F18 -> 12314.637 | H18: =G18 -> 12314.637 | I18: =H18 -> 12314.637 | J18: =I18 -> 12314.637 | K18: =J18 -> 12314.637 | L18: =K18 -> 12314.637 | M18: =L18 -> 12314.637
B19: Diluted WASO | C19: =IncState!C41 -> 13151.754 | D19: =IncState!D41 -> 12678.966 | E19: =IncState!E41 -> 12452.488 | F19: =E19 -> 12452.488 | G19: =F19 -> 12452.488 | H19: =G19 -> 12452.488 | I19: =H19 -> 12452.488 | J19: =I19 -> 12452.488 | K19: =J19 -> 12452.488 | L19: =K19 -> 12452.488 | M19: =L19 -> 12452.488
A21: * | B21: Debt | C21: 44926 | D21: 45291 | E21: 45657 | F21: 46022 | G21: 46387 | H21: 46752 | I21: 47118 | J21: 47483 | K21: =K2 -> 47848 | L21: =L2 -> 48213 | M21: =M2 -> 48579
B22: Interest rate on Revolver | E22: 0.044 | F22: =E22 -> 0.044 | G22: =F22 -> 0.044 | H22: =G22 -> 0.044 | I22: =H22 -> 0.044 | J22: =I22 -> 0.044 | K22: =J22 -> 0.044 | L22: =K22 -> 0.044 | M22: =L22 -> 0.044
B23: Interest rate on long-term debt | E23: 0.044 | F23: =E23 -> 0.044 | G23: =F23 -> 0.044 | H23: =G23 -> 0.044 | I23: =H23 -> 0.044 | J23: =I23 -> 0.044 | K23: =J23 -> 0.044 | L23: =K23 -> 0.044 | M23: =L23 -> 0.044
B24: Interest rate on cash | C24: =IncState!C30/SUM(BalSheet!C16:C17) -> 0.019110072 | D24: =IncState!D30/SUM(BalSheet!D16:D17) -> 0.03484619 | E24: =IncState!E30/SUM(BalSheet!E16:E17) -> 0.046854909 | F24: =E24 -> 0.046854909 | G24: =F24 -> 0.046854909 | H24: =G24 -> 0.046854909 | I24: =H24 -> 0.046854909 | J24: =I24 -> 0.046854909 | K24: =J24 -> 0.046854909 | L24: =K24 -> 0.046854909 | M24: =L24 -> 0.046854909
B26: Issuance of long-term debt | F26: 0 | G26: 0 | H26: 0 | I26: 0 | J26: 0 | K26: 0 | L26: 0 | M26: 0
B27: Repayment of long-term debt | F27: 0 | G27: 0 | H27: 0 | I27: 0 | J27: 0 | K27: 0 | L27: 0 | M27: 0
A29: * | B29: Calcs | C29: 44926 | D29: 45291 | E29: 45657 | F29: 46022 | G29: 46387 | H29: 46752 | I29: 47118 | J29: 47483 | K29: 2030 | L29: =K29+1 -> 2031 | M29: =L29+1 -> 2032
B30: CapEx % of Sales | D30: =32300/IncState!D17 -> 0.10507687 | E30: =52500/IncState!E17 -> 0.14999229 | F30: =CHOOSE(ScenarioCAPEX,P5,P6) -> 0.212 | G30: =CHOOSE(ScenarioCAPEX,Q5,Q6) -> 0.197 | H30: =CHOOSE(ScenarioCAPEX,R5,R6) -> 0.182 | I30: =CHOOSE(ScenarioCAPEX,S5,S6) -> 0.167 | J30: =CHOOSE(ScenarioCAPEX,T5,T6) -> 0.152 | K30: =CHOOSE(ScenarioCAPEX,U5,U6) -> 0.137 | L30: =CHOOSE(ScenarioCAPEX,V5,V6) -> 0.122 | M30: =CHOOSE(ScenarioCAPEX,W5,W6) -> 0.107
B31: Depreciation % of beginning PP&E | D31: =11946/BalSheet!C23 -> 0.10602833 | E31: =15311/BalSheet!D23 -> 0.11396777 | F31: =E31+0.005 -> 0.11896777 | G31: =F31 -> 0.11896777 | H31: =G31 -> 0.11896777 | I31: =H31 -> 0.11896777 | J31: =I31 -> 0.11896777 | K31: =J31 -> 0.11896777 | L31: =K31 -> 0.11896777 | M31: =L31 -> 0.11896777
B32: Share issuance / (repurchases) | C32: -59300 | D32: -62184 | E32: -62047 | F32: 0 | G32: 0 | H32: 0 | I32: 0 | J32: 0 | K32: 0 | L32: 0 | M32: 0
A34: * | B34: Shareholder information | C34: 44926 | D34: 45291 | E34: 45657 | F34: 46022 | G34: 46387 | H34: 46752 | I34: 47118 | J34: 47483 | K34: 2030 | L34: =K34+1 -> 2031 | M34: =L34+1 -> 2032
B35: Dividend payout ratio | C35: =C17 -> 0 | D35: =D17 -> 0 | E35: =E17 -> 0.073543219 | F35: =F17 -> 0.0854 | G35: =G17 -> 0.0854 | H35: =H17 -> 0.0854 | I35: =I17 -> 0.0854 | J35: =J17 -> 0.0854 | ... M35: =M17 -> 0.0854
B36: Basic WASO | C36: =C18 -> 13065.795 | D36: =D18 -> 12592.123 | E36: =E18 -> 12314.637 | F36: =F18 -> 12314.637 | G36: =G18 -> 12314.637 | H36: =H18 -> 12314.637 | I36: =I18 -> 12314.637 | J36: =J18 -> 12314.637 | ... M36: =M18 -> 12314.637
B37: Diluted WASO | C37: =C19 -> 13151.754 | D37: =D19 -> 12678.966 | E37: =E19 -> 12452.488 | F37: =F19 -> 12452.488 | G37: =G19 -> 12452.488 | H37: =H19 -> 12452.488 | I37: =I19 -> 12452.488 | J37: =J19 -> 12452.488 | ... M37: =M19 -> 12452.488
A39: * | B39: Balance Sheet - Assets | C39: 44926 | D39: 45291 | E39: 45657 | F39: 46022 | G39: 46387 | H39: 46752 | I39: 47118 | J39: 47483 | K39: 2030 | L39: =K39+1 -> 2031 | M39: =L39+1 -> 2032
B40: Operating Cash % of sales | C40: =BalSheet!C16/IncState!C17 -> 0.077355782 | D40: =BalSheet!D16/IncState!D17 -> 0.078231846 | E40: =BalSheet!E16/IncState!E17 -> 0.067042266 | F40: =E40 -> 0.067042266 | G40: =F40 -> 0.067042266 | H40: =G40 -> 0.067042266 | I40: =H40 -> 0.067042266 | J40: =I40 -> 0.067042266 | K40: =J40 -> 0.067042266 | L40: =K40 -> 0.067042266 | M40: =L40 -> 0.067042266
B41: Accounts receivable % of sales | C41: =BalSheet!C18/IncState!C17 -> 0.1423369 | D41: =BalSheet!D18/IncState!D17 -> 0.15603428 | E41: =BalSheet!E18/IncState!E17 -> 0.14953517 | F41: =E41 -> 0.14953517 | G41: =F41 -> 0.14953517 | H41: =G41 -> 0.14953517 | I41: =H41 -> 0.14953517 | J41: =I41 -> 0.14953517 | K41: =J41 -> 0.14953517 | L41: =K41 -> 0.14953517 | M41: =L41 -> 0.14953517
B42: Inventories % of COGS | C42: =BalSheet!C19/IncState!C18 -> 0.021156391 | D42: =BalSheet!D19/IncState!D18 -> 0 | E42: =BalSheet!E19/IncState!E18 -> 0 | F42: =E42 -> 0 | G42: =F42 -> 0 | H42: =G42 -> 0 | I42: =H42 -> 0 | J42: =I42 -> 0 | K42: =J42 -> 0 | L42: =K42 -> 0 | M42: =L42 -> 0
B43: Other current assets % of sales | C43: =BalSheet!C20/IncState!C17 -> 0.028656182 | D43: =BalSheet!D20/IncState!D17 -> 0.041152397 | E43: =BalSheet!E20/IncState!E17 -> 0.044894834 | F43: =E43 -> 0.044894834 | G43: =F43 -> 0.044894834 | H43: =G43 -> 0.044894834 | I43: =H43 -> 0.044894834 | J43: =I43 -> 0.044894834 | K43: =J43 -> 0.044894834 | L43: =K43 -> 0.044894834 | M43: =L43 -> 0.044894834
B45: Investments in unconsolidated entities | C45: =BalSheet!C25 -> 30492 | D45: =BalSheet!D25 -> 31008 | E45: =BalSheet!E25 -> 37982 | F45: =E45 -> 37982 | G45: =F45 -> 37982 | H45: =G45 -> 37982 | I45: =H45 -> 37982 | J45: =I45 -> 37982 | K45: =J45 -> 37982 | L45: =K45 -> 37982 | M45: =L45 -> 37982
B46: Other long-term assets % of sales | C46: =BalSheet!C26/IncState!C17 -> 0.092863002 | D46: =BalSheet!D26/IncState!D17 -> 0.11812527 | E46: =BalSheet!E26/IncState!E17 -> 0.13039901 | F46: =E46 -> 0.13039901 | G46: =F46 -> 0.13039901 | H46: =G46 -> 0.13039901 | I46: =H46 -> 0.13039901 | J46: =I46 -> 0.13039901 | K46: =J46 -> 0.13039901 | L46: =K46 -> 0.13039901 | M46: =L46 -> 0.13039901
A48: * | B48: Balance Sheet - Liabilities | C48: 44926 | D48: 45291 | E48: 45657 | F48: 46022 | G48: 46387 | H48: 46752 | I48: 47118 | J48: 47483 | K48: 2030 | L48: =K48+1 -> 2031 | M48: =L48+1 -> 2032
B49: Accounts payable % of COGS | C49: =BalSheet!C32/IncState!C18 -> 0.51814933 | D49: =BalSheet!D32/IncState!D18 -> 0.58258333 | E49: =BalSheet!E32/IncState!E18 -> 0.57472694 | F49: =E49 -> 0.57472694 | G49: =F49 -> 0.57472694 | H49: =G49 -> 0.57472694 | I49: =H49 -> 0.57472694 | J49: =I49 -> 0.57472694 | K49: =J49 -> 0.57472694 | L49: =K49 -> 0.57472694 | M49: =L49 -> 0.57472694
B50: Other current liabilities % of sales | C50: =BalSheet!C33/IncState!C17 -> 0.013817194 | D50: =BalSheet!D33/IncState!D17 -> 0.013458298 | E50: =BalSheet!E33/IncState!E17 -> 0.014387831 | F50: =E50 -> 0.014387831 | G50: =F50 -> 0.014387831 | H50: =G50 -> 0.014387831 | I50: =H50 -> 0.014387831 | J50: =I50 -> 0.014387831 | K50: =J50 -> 0.014387831 | L50: =K50 -> 0.014387831 | M50: =L50 -> 0.014387831
B51: Other long-term liabilities % of sales | C51: =BalSheet!C37/IncState!C17 -> 0.088811184 | D51: =BalSheet!D37/IncState!D17 -> 0.082399136 | E51: =BalSheet!E37/IncState!E17 -> 0.071902016 | F51: =E51 -> 0.071902016 | G51: =F51 -> 0.071902016 | H51: =G51 -> 0.071902016 | I51: =H51 -> 0.071902016 | J51: =I51 -> 0.071902016 | K51: =J51 -> 0.071902016 | L51: =K51 -> 0.071902016 | M51: =L51 -> 0.071902016

Sheet Capex
A1: Capex drivers | G1: Hist. | H1: Hist. | I1: Hist. | J1: Proj. | K1: Proj. | L1: Proj. | M1: Proj. | N1: Proj. | O1: Proj. | P1: Proj. | Q1: Proj.
A2: Total Capex | B2: 85000 | C2: $B | E2: * | F2: Capex Calcs | G2: 44926 | H2: 45291 | I2: 45657 | J2: 46022 | K2: 46387 | L2: 46752 | M2: 47118 | N2: 47483 | O2: 2030 | P2: =O2+1 -> 2031 | Q2: =P2+1 -> 2032
A3: Search & Other | B3: 0.15 | C3: =$C$9*B3*0.001 -> 12.75 | F3: Capex | G3: 24640 | H3: 32251 | I3: 52535 | J3: =Calcs!F7 -> 85180.401 | K3: =Calcs!G7 -> 90181.688 | L3: =Calcs!H7 -> 95929.815 | M3: =Calcs!I7 -> 101805.68 | N3: =Calcs!J7 -> 107662.85 | O3: =Calcs!K7 -> 113279.77 | P3: =Calcs!L7 -> 118328.64 | Q3: =Calcs!M7 -> 122332.3
A4: YT ads | B4: 0.1 | C4: =$C$9*B4*0.001 -> 8.5 | F4: Changes in Capex | G4: =G3/22281-1 -> 0.10587496 | H4: =H3/G3-1 -> 0.30888799 | I4: =I3/H3-1 -> 0.62894174 | J4: =J3/I3-1 -> 0.62140289 | K4: =K3/J3-1 -> 0.058714064 | L4: =L3/K3-1 -> 0.063739404 | M4: =M3/L3-1 -> 0.061251664 | N4: =N3/M3-1 -> 0.057532871 | O4: =O3/N3-1 -> 0.052171366 | ... Q4: =Q3/P3-1 -> 0.033835117
A5: Google network | B5: 0.05 | C5: =$C$9*B5*0.001 -> 4.25 | E5: * | F5: Changes in segment revenue
A6: Subscription/Platforms/Devices | B6: 0.07 | C6: =$C$9*B6*0.001 -> 5.95 | F6: Google Search & Other | G6: =Revenues!D3 -> 162450 | H6: =Revenues!I3 -> 175033 | I6: =Revenues!N3 -> 198084 | J6: =Revenues!S3 -> 222342.3 | K6: =Revenues!T3 -> 249571.39 | L6: =Revenues!U3 -> 280135.07 | M6: =Revenues!V3 -> 314441.73 | N6: =Revenues!W3 -> 352949.75 | O6: =Revenues!X3 -> 396173.64 | P6: =Revenues!Y3 -> 444690.93 | Q6: =Revenues!Z3 -> 499149.88
A7: Google cloud | B7: 0.6 | C7: =$C$9*B7*0.001 -> 51 | F7: Delta impact | H7: =(H6-G6)*0.001 -> 12.583 | I7: =(I6-H6)*0.001 -> 23.051 | J7: =(J6-I6)*0.001 -> 24.2583 | K7: =(K6-J6)*0.001 -> 27.229086 | L7: =(L6-K6)*0.001 -> 30.563688 | M7: =(M6-L6)*0.001 -> 34.306661 | N7: =(N6-M6)*0.001 -> 38.508016 | O7: =(O6-N6)*0.001 -> 43.22389 | ... Q7: =(Q6-P6)*0.001 -> 54.458947
A8: Other Bets | B8: 0.03 | C8: =$C$9*B8*0.001 -> 2.55 | F8: Rev/$B Capex | H8: =H7/$C$3 -> 0.98690196 | I8: =I7/$C$3 -> 1.8079216 | J8: =J7/C3 -> 1.9026118 | K8: =K7/$C$3 -> 2.1356146 | L8: =L7/$C$3 -> 2.397152 | M8: =M7/$C$3 -> 2.6907185 | N8: =N7/$C$3 -> 3.0202366 | O8: =O7/$C$3 -> 3.390109 | P8: =P7/$C$3 -> 3.8052777 | Q8: =Q7/$C$3 -> 4.2712899
A9: Total Weighting | B9: =SUM(B3:B8) -> 1 | C9: =B9*$B$2 -> 85000
F10: Youtube | G10: =Revenues!D6 -> 29243 | H10: =Revenues!I6 -> 31510 | I10: =Revenues!N6 -> 36147 | J10: =Revenues!S6 -> 40426.784
F11: Delta impact | H11: =(H10-G10)*0.001 -> 2.267 | I11: =(I10-H10)*0.001 -> 4.637 | J11: =(J10-I10)*0.001 -> 4.2797844
F12: Rev/$B Capex | J12: =J11/C4 -> 0.50350404
F14: Google Network | G14: =Revenues!D9 -> 32780 | H14: =Revenues!I9 -> 31312 | I14: =Revenues!N9 -> 30359 | J14: =Revenues!S9 -> 30267.02
F15: Delta impact | H15: =(H14-G14)*0.001 -> -1.468 | I15: =(I14-H14)*0.001 -> -0.953 | J15: =(J14-I14)*0.001 -> -0.09198
F16: Rev/$B Capex | J16: =J15/C5 -> -0.021642353
F18: Subscriptions | G18: =Revenues!D16 -> 29055 | H18: =Revenues!I16 -> 34688 | I18: =Revenues!N16 -> 40340 | J18: =Revenues!S16 -> 48328.8
F19: Delta impact | H19: =(H18-G18)*0.001 -> 5.633 | I19: =(I18-H18)*0.001 -> 5.652 | J19: =(J18-I18)*0.001 -> 7.9888
F20: Rev/$B Capex | J20: =J19/C6 -> 1.3426555
K21: =K22/J22-1 -> 0.24792249 | L21: =L22/K22-1 -> 0.29969234 | M21: =M22/L22-1 -> 0.29969234 | N21: =N22/M22-1 -> 0.29969234 | O21: =O22/N22-1 -> 0.29969234 | P21: =P22/O22-1 -> 0.29969234 | Q21: =Q22/P22-1 -> 0.29969234
F22: Google Cloud | G22: 26280 | H22: 33088 | I22: 43229 | J22: =Revenues!S19 -> 58515.2 | K22: 73022.434 | L22: 94906.698 | M22: 123349.51 | N22: 160316.41 | O22: 208362.01 | P22: 270806.51 | Q22: 351965.14
F23: Delta impact | H23: =(H22-G22)*0.001 -> 6.808 | I23: =(I22-H22)*0.001 -> 10.141 | J23: =(J22-I22)*0.001 -> 15.2862 | K23: =(K22-J22)*0.001 -> 14.507234 | L23: =(L22-K22)*0.001 -> 21.884264 | M23: =(M22-L22)*0.001 -> 28.44281 | N23: =(N22-M22)*0.001 -> 36.966902 | O23: =(O22-N22)*0.001 -> 48.045599 | ... Q23: =(Q22-P22)*0.001 -> 81.158635
F24: Rev/$B Capex | H24: =H23/$C$7 -> 0.1334902 | I24: =I23/$C$7 -> 0.19884314 | J24: =J23/$C$7 -> 0.29972941 | K24: =K23/($B$7*K3*0.001) -> 0.26811123 | L24: =L23/($B$7*L3*0.001) -> 0.38021311 | M24: =M23/($B$7*M3*0.001) -> 0.4656389 | N24: =N23/($B$7*N3*0.001) -> 0.57226336 | O24: =O23/($B$7*O3*0.001) -> 0.70688704 | P24: =P23/($B$7*P3*0.001) -> 0.87953488 | Q24: =Q23/($B$7*Q3*0.001) -> 1.1057128
F25: Rev/$B Capex Mean | K25: 0.4 | L25: =K25+0.25 -> 0.65 | M25: =L25+0.25 -> 0.9 | N25: =M25+0.25 -> 1.15 | O25: =N25+0.25 -> 1.4 | P25: =O25+0.25 -> 1.65 | Q25: =P25+0.25 -> 1.9
F26: Rev/$B Capex increase | K26: =K25/K24 -> 1.4919181 | L26: =L25/L24 -> 1.7095676 | M26: =M25/M24 -> 1.9328282 | N26: =N25/N24 -> 2.0095643 | O26: =O25/O24 -> 1.9805145 | P26: =P25/P24 -> 1.8759915 | Q26: =Q25/Q24 -> 1.7183485
F27: Delta Increase | K27: =K23*K26 -> 21.643605 | L27: =L23*L26 -> 37.412628 | M27: =M23*M26 -> 54.975065 | N27: =N23*N26 -> 74.287366 | O27: =O23*O26 -> 95.155004 | P27: =P23*P26 -> 117.14535 | Q27: =Q23*Q26 -> 139.45882
F28: Adjusted Google Clound Rev | K28: =J22+(K27*1000) -> 80158.805 | L28: =K22+(L27*1000) -> 110435.06 | M28: =L22+(M27*1000) -> 149881.76 | N28: =M22+(N27*1000) -> 197636.87 | O28: =N22+(O27*1000) -> 255471.41 | P28: =O22+(P27*1000) -> 325507.36 | Q28: =P22+(Q27*1000) -> 410265.33
F29: Adjust y/y% | K29: =K28/J22-1 -> 0.36988005 | L29: =L28/K28-1 -> 0.37770345 | M29: =M28/L28-1 -> 0.35719363 | N29: =N28/M28-1 -> 0.31861855 | O29: =O28/N28-1 -> 0.29263031 | P29: =P28/O28-1 -> 0.27414396 | Q29: =Q28/P28-1 -> 0.26038726
F31: Other Bets | G31: =Revenues!D22 -> 1068 | H31: =Revenues!I22 -> 1527 | I31: =Revenues!N22 -> 1648 | J31: =Revenues!S22 -> 1766.2385
F32: Delta impact | H32: =(H31-G31)*0.001 -> 0.459 | I32: =(I31-H31)*0.001 -> 0.121 | J32: =(J31-I31)*0.001 -> 0.11823846
F33: Rev/$B Capex | J33: =J32/C8 -> 0.046368024
K35: 0.41491776 | L35: 0.33944567 | M35: 0.32620503 | N35: 0.3167992 | O35: 0.31008779 | P35: 0.30532718 | Q35: 0.3020102

Sheet Calcs
A1: =CoName -> Alphabet Inc. | C1: Hist. | D1: Hist. | E1: Hist. | F1: Proj. | G1: Proj. | H1: Proj. | I1: Proj. | J1: Proj. | K1: Proj. | L1: Proj. | M1: Proj.
A2: Net PP&E | C2: 2022 | D2: =DATE(YEAR(E2)-1,MONTH(E2),DAY(E2)) -> 44959 | E2: =DATE(YEAR(F2)-1,MONTH(F2),DAY(F2)) -> 45324 | F2: =Inputs!C6 -> 45690 | G2: =DATE(YEAR(F2)+1,MONTH(F2),DAY(F2)) -> 46055 | H2: =DATE(YEAR(G2)+1,MONTH(G2),DAY(G2)) -> 46420 | I2: =DATE(YEAR(H2)+1,MONTH(H2),DAY(H2)) -> 46785 | J2: =DATE(YEAR(I2)+1,MONTH(I2),DAY(I2)) -> 47151 | K2: =DATE(YEAR(J2)+1,MONTH(J2),DAY(J2)) -> 47516 | L2: =DATE(YEAR(K2)+1,MONTH(K2),DAY(K2)) -> 47881 | M2: =DATE(YEAR(L2)+1,MONTH(L2),DAY(L2)) -> 48246
B3: Capital expenditure % of sales | F3: =Assumptions!F30 -> 0.212 | G3: =Assumptions!G30 -> 0.197 | H3: =Assumptions!H30 -> 0.182 | I3: =Assumptions!I30 -> 0.167 | J3: =Assumptions!J30 -> 0.152 | K3: =Assumptions!K30 -> 0.137 | L3: =Assumptions!L30 -> 0.122 | M3: =Assumptions!M30 -> 0.107
B4: Depreciation % of PP&E | F4: =Assumptions!F31 -> 0.11896777 | G4: =F4 -> 0.11896777 | H4: =G4 -> 0.11896777 | I4: =H4 -> 0.11896777 | J4: =I4 -> 0.11896777 | K4: =J4 -> 0.11896777 | L4: =K4 -> 0.11896777 | M4: =L4 -> 0.11896777
B6: Beginning PP&E | F6: =E9 -> 171036 | G6: =F9 -> 235868.63 | H6: =G9 -> 297989.55 | I6: =H9 -> 358468.22 | J6: =I9 -> 417627.73 | K6: =J9 -> 475606.34 | L6: =K9 -> 532304.28 | M6: =L9 -> 587305.86
B7: Capex | F7: =IncState!F17*Calcs!F3 -> 85180.401 | G7: =IncState!G17*Calcs!G3 -> 90181.688 | H7: =IncState!H17*Calcs!H3 -> 95929.815 | I7: =IncState!I17*Calcs!I3 -> 101805.68 | J7: =IncState!J17*Calcs!J3 -> 107662.85 | K7: =IncState!K17*Calcs!K3 -> 113279.77 | L7: =IncState!L17*Calcs!L3 -> 118328.64 | M7: =IncState!M17*Calcs!M3 -> 122332.3
B8: Depreciation | F8: =F6*F4 -> 20347.771 | G8: =G6*G4 -> 28060.765 | H8: =H6*H4 -> 35451.152 | I8: =I6*I4 -> 42646.164 | J8: =J6*J4 -> 49684.239 | K8: =K6*K4 -> 56581.825 | L8: =L6*L4 -> 63327.053 | M8: =M6*M4 -> 69870.468
B9: Ending PP&E | E9: =BalSheet!E23 -> 171036 | F9: =F6+F7-F8 -> 235868.63 | G9: =G6+G7-G8 -> 297989.55 | H9: =H6+H7-H8 -> 358468.22 | I9: =I6+I7-I8 -> 417627.73 | J9: =J6+J7-J8 -> 475606.34 | K9: =K6+K7-K8 -> 532304.28 | L9: =L6+L7-L8 -> 587305.86 | M9: =M6+M7-M8 -> 639767.69
A11: Equity | C11: 44926 | D11: 45291 | E11: 45657 | F11: 46022 | G11: 46387 | H11: 46752 | I11: 47118 | J11: 47483 | K11: =K2 -> 47516 | L11: =L2 -> 47881 | M11: =M2 -> 48246
B12: Share issuance/(repurchases) | F12: =Assumptions!F32 -> 0 | G12: =Assumptions!G32 -> 0 | H12: =Assumptions!H32 -> 0 | I12: =Assumptions!I32 -> 0 | J12: =Assumptions!J32 -> 0 | K12: =Assumptions!K32 -> 0 | L12: =Assumptions!L32 -> 0 | M12: =Assumptions!M32 -> 0
B14: Beginning balance | F14: =E18 -> 325084 | G14: =F18 -> 420745.76 | H14: =G18 -> 530931.44 | I14: =H18 -> 657800.37 | J14: =I18 -> 804533.62 | K14: =J18 -> 975022.21 | L14: =K18 -> 1174045.9 | M14: =L18 -> 1407500.8
B15: Net income | F15: =IncState!F36 -> 104594.1 | G15: =IncState!G36 -> 120474.18 | H15: =IncState!H36 -> 138715.2 | I15: =IncState!I36 -> 160434.35 | J15: =IncState!J36 -> 186407.81 | K15: =IncState!K36 -> 217607.38 | L15: =IncState!L36 -> 255253.59 | M15: =IncState!M36 -> 300884.07
B16: Dividends paid | F16: =IncState!F38 -> 8932.336 | G16: =IncState!G38 -> 10288.495 | H16: =IncState!H38 -> 11846.278 | I16: =IncState!I38 -> 13701.093 | J16: =IncState!J38 -> 15919.227 | K16: =IncState!K38 -> 18583.67 | L16: =IncState!L38 -> 21798.657 | M16: =IncState!M38 -> 25695.499
B17: Share issuance / (repurchase) | F17: =F12 -> 0 | G17: =G12 -> 0 | H17: =H12 -> 0 | I17: =I12 -> 0 | J17: =J12 -> 0 | K17: =K12 -> 0 | L17: =L12 -> 0 | M17: =M12 -> 0
B18: Ending balance | E18: =BalSheet!E40 -> 325084 | F18: =F14+F15-F16-F17 -> 420745.76 | G18: =G14+G15-G16-G17 -> 530931.44 | H18: =H14+H15-H16-H17 -> 657800.37 | I18: =I14+I15-I16-I17 -> 804533.62 | J18: =J14+J15-J16-J17 -> 975022.21 | K18: =K14+K15-K16-K17 -> 1174045.9 | L18: =L14+L15-L16-L17 -> 1407500.8 | M18: =M14+M15-M16-M17 -> 1682689.4
A20: OWC | C20: 44926 | D20: 45291 | E20: 45657 | F20: 46022 | G20: 46387 | H20: 46752 | I20: 47118 | J20: 47483 | K20: =K11 -> 47516 | L20: =L11 -> 47881 | M20: =M11 -> 48246
B21: Operating Cash | E21: =BalSheet!E16 -> 23466 | F21: =BalSheet!F16 -> 26937.203 | G21: =BalSheet!G16 -> 30690.278 | H21: =BalSheet!H16 -> 35337.1 | I21: =BalSheet!I16 -> 40869.96 | J21: =BalSheet!J16 -> 47486.588 | K21: =BalSheet!K16 -> 55434.542 | L21: =BalSheet!L16 -> 65024.753 | M21: =BalSheet!M16 -> 76648.921
B22: =BalSheet!B19 -> Inventories | E22: =BalSheet!E19 -> 0 | F22: =BalSheet!F19 -> 0 | G22: =BalSheet!G19 -> 0 | H22: =BalSheet!H19 -> 0 | I22: =BalSheet!I19 -> 0 | J22: =BalSheet!J19 -> 0 | K22: =BalSheet!K19 -> 0 | L22: =BalSheet!L19 -> 0 | M22: =BalSheet!M19 -> 0
B23: =BalSheet!B18 -> Accounts receivable | E23: =BalSheet!E18 -> 52340 | F23: =BalSheet!F18 -> 60082.384 | G23: =BalSheet!G18 -> 68453.471 | H23: =BalSheet!H18 -> 78818.027 | I23: =BalSheet!I18 -> 91158.855 | J23: =BalSheet!J18 -> 105916.99 | K23: =BalSheet!K18 -> 123644.59 | L23: =BalSheet!L18 -> 145035.18 | M23: =BalSheet!M18 -> 170962.44
B24: Other current assets | E24: =BalSheet!E20 -> 15714 | F24: =BalSheet!F20 -> 18038.49 | G24: =BalSheet!G20 -> 20551.736 | H24: =BalSheet!H20 -> 23663.479 | I24: =BalSheet!I20 -> 27368.556 | J24: =BalSheet!J20 -> 31799.38 | K24: =BalSheet!K20 -> 37121.725 | L24: =BalSheet!L20 -> 43543.807 | M24: =BalSheet!M20 -> 51327.927
B25: Accounts payables | E25: =BalSheet!E32 -> 84086 | F25: =BalSheet!F32 -> 96524.405 | G25: =BalSheet!G32 -> 109972.84 | H25: =BalSheet!H32 -> 126623.86 | I25: =BalSheet!I32 -> 146449.82 | J25: =BalSheet!J32 -> 170159.26 | K25: =BalSheet!K32 -> 198639.26 | L25: =BalSheet!L32 -> 233003.98 | M25: =BalSheet!M32 -> 274657
B26: Other current liabilities | E26: =BalSheet!E33 -> 5036 | F26: =BalSheet!F33 -> 5780.9493 | G26: =BalSheet!G33 -> 6586.3905 | H26: =BalSheet!H33 -> 7583.6375 | I26: =BalSheet!I33 -> 8771.0354 | J26: =BalSheet!J33 -> 10191.019 | K26: =BalSheet!K33 -> 11896.717 | L26: =BalSheet!L33 -> 13954.856 | M26: =BalSheet!M33 -> 16449.5
B28: OWC | E28: =SUM(E21:E24)-SUM(E25:E26) -> 2398 | F28: =SUM(F21:F24)-SUM(F25:F26) -> 2752.7237 | G28: =SUM(G21:G24)-SUM(G25:G26) -> 3136.2519 | H28: =SUM(H21:H24)-SUM(H25:H26) -> 3611.1125 | I28: =SUM(I21:I24)-SUM(I25:I26) -> 4176.5177 | J28: =SUM(J21:J24)-SUM(J25:J26) -> 4852.6736 | K28: =SUM(K21:K24)-SUM(K25:K26) -> 5664.8782 | L28: =SUM(L21:L24)-SUM(L25:L26) -> 6644.9057 | M28: =SUM(M21:M24)-SUM(M25:M26) -> 7832.7841
B29: Change in OWC | F29: =E28-F28 -> -354.72367 | G29: =F28-G28 -> -383.52821 | H29: =G28-H28 -> -474.86063 | I29: =H28-I28 -> -565.40514 | J29: =I28-J28 -> -676.15594 | K29: =J28-K28 -> -812.20465 | L29: =K28-L28 -> -980.0275 | M29: =L28-M28 -> -1187.8784

Sheet Debt
A1: =CoName -> Alphabet Inc. | C1: Hist. | D1: Hist. | E1: Hist. | F1: Proj. | G1: Proj. | H1: Proj. | I1: Proj. | J1: Proj. | K1: Proj. | L1: Proj. | M1: Proj.
A2: Assumptions | C2: 44926 | D2: 45291 | E2: 45657 | F2: 46022 | G2: 46387 | H2: 46752 | I2: 47118 | J2: 47483 | K2: =2030 -> 2030 | L2: =K2+1 -> 2031 | M2: =L2+1 -> 2032
B3: Interest rate on revolver | F3: =Assumptions!F22 -> 0.044 | G3: =Assumptions!G22 -> 0.044 | H3: =Assumptions!H22 -> 0.044 | I3: =Assumptions!I22 -> 0.044 | J3: =Assumptions!J22 -> 0.044 | K3: =Assumptions!K22 -> 0.044 | L3: =Assumptions!L22 -> 0.044 | M3: =Assumptions!M22 -> 0.044
B4: Interest rate on long-term debt | F4: =Assumptions!F23 -> 0.044 | G4: =Assumptions!G23 -> 0.044 | H4: =Assumptions!H23 -> 0.044 | I4: =Assumptions!I23 -> 0.044 | J4: =Assumptions!J23 -> 0.044 | K4: =Assumptions!K23 -> 0.044 | L4: =Assumptions!L23 -> 0.044 | M4: =Assumptions!M23 -> 0.044
B5: Interest rate on cash | F5: =Assumptions!F24 -> 0.046854909 | G5: =Assumptions!G24 -> 0.046854909 | H5: =Assumptions!H24 -> 0.046854909 | I5: =Assumptions!I24 -> 0.046854909 | J5: =Assumptions!J24 -> 0.046854909 | K5: =Assumptions!K24 -> 0.046854909 | L5: =Assumptions!L24 -> 0.046854909 | M5: =Assumptions!M24 -> 0.046854909
B7: Issuance of long-term debt | F7: =Assumptions!F26 -> 0 | G7: =Assumptions!G26 -> 0 | H7: =Assumptions!H26 -> 0 | I7: =Assumptions!I26 -> 0 | J7: =Assumptions!J26 -> 0 | K7: =Assumptions!K26 -> 0 | L7: =Assumptions!L26 -> 0 | M7: =Assumptions!M26 -> 0
B8: Repayment of long-term debt | F8: =Assumptions!F27 -> 0 | G8: =Assumptions!G27 -> 0 | H8: =Assumptions!H27 -> 0 | I8: =Assumptions!I27 -> 0 | J8: =Assumptions!J27 -> 0 | K8: =Assumptions!K27 -> 0 | L8: =Assumptions!L27 -> 0 | M8: =Assumptions!M27 -> 0
A10: Revolver | C10: =C2 -> 44926 | D10: =D2 -> 45291 | E10: =E2 -> 45657 | F10: =F2 -> 46022 | G10: =G2 -> 46387 | H10: =H2 -> 46752 | I10: =I2 -> 47118 | J10: =J2 -> 47483 | ... M10: =M2 -> 2032
B11: Balance | E11: 0 | F11: 0 | G11: 0 | H11: 0 | I11: 0 | J11: 0 | K11: 0 | L11: 0 | M11: 0
B12: Interest rate | F12: 0 | G12: 0 | H12: 0 | I12: 0 | J12: 0 | K12: 0 | L12: 0 | M12: 0
B13: Interest expense | F13: 0 | G13: 0 | H13: 0 | I13: 0 | J13: 0 | K13: 0 | L13: 0 | M13: 0
A15: Long term debt | C15: =C10 -> 44926 | D15: =D10 -> 45291 | E15: =E10 -> 45657 | F15: =F10 -> 46022 | G15: =G10 -> 46387 | H15: =H10 -> 46752 | I15: =I10 -> 47118 | J15: =J10 -> 47483 | ... M15: =M10 -> 2032
B16: Beginning balance | E16: 0 | F16: =E19 -> 10883 | G16: =F19 -> 10883 | H16: =G19 -> 10883 | I16: =H19 -> 10883 | J16: =I19 -> 10883 | K16: =J19 -> 10883 | L16: =K19 -> 10883 | M16: =L19 -> 10883
B17: Issuance | E17: 0 | F17: 0 | G17: 0 | H17: 0 | I17: 0 | J17: 0 | K17: 0 | L17: 0 | M17: 0
B18: Repayment | E18: 0 | F18: 0 | G18: 0 | H18: 0 | I18: 0 | J18: 0 | K18: 0 | L18: 0 | M18: 0
B19: Ending balance | E19: =BalSheet!E36 -> 10883 | F19: =F16+F17-F18 -> 10883 | G19: =G16+G17-G18 -> 10883 | H19: =H16+H17-H18 -> 10883 | I19: =I16+I17-I18 -> 10883 | J19: =J16+J17-J18 -> 10883 | K19: =K16+K17-K18 -> 10883 | L19: =L16+L17-L18 -> 10883 | M19: =M16+M17-M18 -> 10883
B20: Interest rate | E20: 0 | F20: =-F4 -> -0.044 | G20: =-G4 -> -0.044 | H20: =-H4 -> -0.044 | I20: =-I4 -> -0.044 | J20: =-J4 -> -0.044 | K20: =-K4 -> -0.044 | L20: =-L4 -> -0.044 | M20: =-M4 -> -0.044
B21: Interest expense | E21: 0 | F21: =F19*F20 -> -478.852 | G21: =G19*G20 -> -478.852 | H21: =H19*H20 -> -478.852 | I21: =I19*I20 -> -478.852 | J21: =J19*J20 -> -478.852 | K21: =K19*K20 -> -478.852 | L21: =L19*L20 -> -478.852 | M21: =M19*M20 -> -478.852
A23: Debt summary | C23: =C15 -> 44926 | D23: =D15 -> 45291 | E23: =E15 -> 45657 | F23: =F15 -> 46022 | G23: =G15 -> 46387 | H23: =H15 -> 46752 | I23: =I15 -> 47118 | J23: =J15 -> 47483 | ... M23: =M15 -> 2032
B24: Revolver
B25: Total long term debt
B26: Total debt
B28: Total interest expense
A30: Interest income | C30: =C10 -> 44926 | D30: =D10 -> 45291 | E30: =E10 -> 45657 | F30: =F10 -> 46022 | G30: =G10 -> 46387 | H30: =H10 -> 46752 | I30: =I10 -> 47118 | J30: =J10 -> 47483 | ... M30: =M10 -> 2032
B31: Excess Cash | F31: =BalSheet!F17 -> 99636.649 | G31: =BalSheet!G17 -> 144043.18 | H31: =BalSheet!H17 -> 205904.04 | I31: =BalSheet!I17 -> 288084.74 | J31: =BalSheet!J17 -> 394145.3 | K31: =BalSheet!K17 -> 528723.96 | L31: =BalSheet!L17 -> 697829.45 | M31: =BalSheet!M17 -> 909225.77
B32: Interest rate | F32: =F5 -> 0.046854909 | G32: =G5 -> 0.046854909 | H32: =H5 -> 0.046854909 | I32: =I5 -> 0.046854909 | J32: =J5 -> 0.046854909 | K32: =K5 -> 0.046854909 | L32: =L5 -> 0.046854909 | M32: =M5 -> 0.046854909
B33: Interest income | F33: =F31*F32 -> 4668.4661 | G33: =G31*G32 -> 6749.1298 | H33: =H31*H32 -> 9647.615 | I33: =I31*I32 -> 13498.184 | J33: =J31*J32 -> 18467.642 | K33: =K31*K32 -> 24773.313 | L33: =L31*L32 -> 32696.735 | M33: =M31*M32 -> 42601.69

Sheet IncState
A1: =CoName -> Alphabet Inc. | C1: Hist. | D1: Hist. | E1: Hist. | F1: Proj. | G1: Proj. | H1: Proj. | I1: Proj. | J1: Proj. | K1: Proj. | L1: Proj. | M1: Proj.
A2: Assumptions
B4: Revenue growth | F4: =Assumptions!F9 -> 0.1479248 | G4: =Assumptions!G9 -> 0.13932681 | H4: =Assumptions!H9 -> 0.15141023 | I4: =Assumptions!I9 -> 0.15657367 | J4: =Assumptions!J9 -> 0.16189467 | K4: =Assumptions!K9 -> 0.16737261 | L4: =Assumptions!L9 -> 0.17300063 | M4: =Assumptions!M9 -> 0.17876527
B5: Cost of goods sold as % of sales | C5: =Assumptions!C10 -> 0.44620557 | D5: =Assumptions!D10 -> 0.43374952 | E5: =Assumptions!E10 -> 0.41799565 | F5: =Assumptions!F10 -> 0.41799565 | G5: =Assumptions!G10 -> 0.41799565 | H5: =Assumptions!H10 -> 0.41799565 | I5: =Assumptions!I10 -> 0.41799565 | J5: =Assumptions!J10 -> 0.41799565 | ... M5: =Assumptions!M10 -> 0.41799565
B6: R&D % of sales | C6: =Assumptions!C11 -> 0.1396569 | D6: =Assumptions!D11 -> 0.14778102 | E6: =Assumptions!E11 -> 0.14092418 | F6: =Assumptions!F11 -> 0.14092418 | G6: =F6 -> 0.14092418 | H6: =G6 -> 0.14092418 | I6: =H6 -> 0.14092418 | J6: =I6 -> 0.14092418 | K6: =J6 -> 0.14092418 | L6: =K6 -> 0.14092418 | M6: =L6 -> 0.14092418
B7: SG&A % of sales | C7: =Assumptions!C12 -> 0.14952481 | D7: =Assumptions!D12 -> 0.14425135 | E7: =Assumptions!E12 -> 0.1199824 | F7: =Assumptions!F12 -> 0.1199824 | G7: =F7 -> 0.1199824 | H7: =G7 -> 0.1199824 | I7: =H7 -> 0.1199824 | J7: =I7 -> 0.1199824 | K7: =J7 -> 0.1199824 | L7: =K7 -> 0.1199824 | M7: =L7 -> 0.1199824
B8: Amortization amount | C8: =Assumptions!C13 -> 0 | D8: =Assumptions!D13 -> 0 | E8: =Assumptions!E13 -> 0 | F8: =Assumptions!F13 -> 0 | G8: =F8 -> 0 | H8: =G8 -> 0 | I8: =H8 -> 0 | J8: =I8 -> 0 | K8: =J8 -> 0 | L8: =K8 -> 0 | M8: =L8 -> 0
B9: Non recurring items, amount | C9: =Assumptions!C14 -> 0 | D9: =Assumptions!D14 -> 0 | E9: =Assumptions!E14 -> 0 | F9: =Assumptions!F14 -> -1400 | G9: =Assumptions!G14 -> 0 | H9: =Assumptions!H14 -> 0 | I9: =Assumptions!I14 -> 0 | J9: =Assumptions!J14 -> 0 | ... M9: =Assumptions!M14 -> 0
B10: Other income (expense), amt | F10: =Assumptions!F15 -> 0 | G10: =Assumptions!G15 -> 0 | H10: =Assumptions!H15 -> 0 | I10: =Assumptions!I15 -> 0 | J10: =Assumptions!J15 -> 0 | K10: =Assumptions!K15 -> 0 | L10: =Assumptions!L15 -> 0 | M10: =Assumptions!M15 -> 0
B11: Effective tax rate | C11: =1-C36/C33 -> 0.15920817 | D11: =1-D36/D33 -> 0.13950386 | E11: =1-E36/E33 -> 0.16439511 | F11: =Assumptions!F16 -> 0.18039511 | G11: =Assumptions!G16 -> 0.18039511 | H11: =Assumptions!H16 -> 0.18039511 | I11: =Assumptions!I16 -> 0.18039511 | J11: =Assumptions!J16 -> 0.18039511 | K11: =Assumptions!K16 -> 0.18039511 | L11: =Assumptions!L16 -> 0.18039511 | M11: =Assumptions!M16 -> 0.18039511
B12: Dividend Payout Rate | C12: 0 | D12: 0 | E12: =7363/E36 -> 0.073543219 | F12: 0.0854 | G12: =F12 -> 0.0854 | H12: =G12 -> 0.0854 | I12: =H12 -> 0.0854 | J12: =I12 -> 0.0854 | K12: =J12 -> 0.0854 | L12: =K12 -> 0.0854 | M12: =L12 -> 0.0854
B13: Basic WASO | F13: =Assumptions!F18 -> 12314.637 | G13: =Assumptions!G18 -> 12314.637 | H13: =Assumptions!H18 -> 12314.637 | I13: =Assumptions!I18 -> 12314.637 | J13: =Assumptions!J18 -> 12314.637 | K13: =Assumptions!K18 -> 12314.637 | L13: =Assumptions!L18 -> 12314.637 | M13: =Assumptions!M18 -> 12314.637
B14: Diluted WASO | F14: =Assumptions!F19 -> 12452.488 | G14: =Assumptions!G19 -> 12452.488 | H14: =Assumptions!H19 -> 12452.488 | I14: =Assumptions!I19 -> 12452.488 | J14: =Assumptions!J19 -> 12452.488 | K14: =Assumptions!K19 -> 12452.488 | L14: =Assumptions!L19 -> 12452.488 | M14: =Assumptions!M19 -> 12452.488
A16: Income statement | C16: =C39 -> 44926 | D16: =D39 -> 45291 | E16: =E39 -> 45657 | F16: =F39 -> 46022 | G16: =G39 -> 46387 | H16: =H39 -> 46752 | I16: =I39 -> 47118 | J16: =J39 -> 47483 | ... M16: =M39 -> 2032
B17: Revenue | C17: =Revenues!D26 -> 282836 | D17: =Revenues!I26 -> 307394 | E17: =Revenues!N26 -> 350018 | F17: =E17*(1+F4) -> 401794.34 | G17: =F17*(1+G4) -> 457775.07 | H17: =G17*(1+H4) -> 527086.9 | I17: =H17*(1+I4) -> 609614.83 | J17: =I17*(1+J4) -> 708308.22 | K17: =J17*(1+K4) -> 826859.61 | L17: =K17*(1+L4) -> 969906.85 | M17: =L17*(1+M4) -> 1143292.5
B18: COGS | C18: 126203 | D18: 133332 | E18: 146306 | F18: =F17*F5 -> 167948.29 | G18: =G17*G5 -> 191347.98 | H18: =H17*H5 -> 220320.03 | I18: =I17*I5 -> 254816.34 | J18: =J17*J5 -> 296069.75 | K18: =K17*K5 -> 345623.72 | L18: =L17*L5 -> 405416.84 | M18: =M17*M5 -> 477891.29
B19: R&D | C19: 39500 | D19: 45427 | E19: 49326 | F19: =F17*F6 -> 56622.539 | G19: =G17*G6 -> 64511.576 | H19: =H17*H6 -> 74279.289 | I19: =I17*I6 -> 85909.47 | J19: =J17*J6 -> 99817.755 | K19: =K17*K6 -> 116524.51 | L19: =L17*L6 -> 136683.33 | M19: =M17*M6 -> 161117.56
B20: SG&A | C20: =26567+15724 -> 42291 | D20: =27917+16425 -> 44342 | E20: =27808+14188 -> 41996 | F20: =F17*F7 -> 48208.25 | G20: =G17*G7 -> 54924.952 | H20: =H17*H7 -> 63241.151 | I20: =I17*I7 -> 73143.051 | J20: =J17*J7 -> 84984.52 | K20: =K17*K7 -> 99208.601 | L20: =L17*L7 -> 116371.75 | M20: =M17*M7 -> 137174.98
A21: * | B21: EBIT | C21: =C17-SUM(C18:C20) -> 74842 | D21: =D17-SUM(D18:D20) -> 84293 | E21: =E17-SUM(E18:E20) -> 112390 | F21: =F17-SUM(F18:F20) -> 129015.27 | G21: =G17-SUM(G18:G20) -> 146990.55 | H21: =H17-SUM(H18:H20) -> 169246.43 | I21: =I17-SUM(I18:I20) -> 195745.96 | J21: =J17-SUM(J18:J20) -> 227436.19 | ... M21: =M17-SUM(M18:M20) -> 367108.68
B23: Depreciation | C23: 13475 | D23: 11946 | E23: 15311 | F23: =Calcs!F8 -> 20347.771 | G23: =Calcs!G8 -> 28060.765 | H23: =Calcs!H8 -> 35451.152 | I23: =Calcs!I8 -> 42646.164 | J23: =Calcs!J8 -> 49684.239 | K23: =Calcs!K8 -> 56581.825 | L23: =Calcs!L8 -> 63327.053 | M23: =Calcs!M8 -> 69870.468
B24: Amortization | C24: 0 | D24: 0 | E24: 0 | F24: =F8 -> 0 | G24: =G8 -> 0 | H24: =H8 -> 0 | I24: =I8 -> 0 | J24: =J8 -> 0 | K24: =K8 -> 0 | L24: =L8 -> 0 | M24: =M8 -> 0
A25: * | B25: EBITDA | C25: =C21+C23 -> 88317 | D25: =D21+D23 -> 96239 | E25: =E21+E23 -> 127701 | F25: =F21+SUM(F23:F24) -> 149363.04 | G25: =G21+SUM(G23:G24) -> 175051.32 | H25: =H21+SUM(H23:H24) -> 204697.58 | I25: =I21+SUM(I23:I24) -> 238392.13 | J25: =J21+SUM(J23:J24) -> 277120.43 | K25: =K21+SUM(K23:K24) -> 322084.6 | L25: =L21+SUM(L23:L24) -> 374761.98 | M25: =M21+SUM(M23:M24) -> 436979.15
B27: Non-recurring items | C27: 0 | D27: 0 | E27: 0 | F27: =F9 -> -1400 | G27: =G9 -> 0 | H27: =H9 -> 0 | I27: =I9 -> 0 | J27: =J9 -> 0 | K27: =K9 -> 0 | L27: =L9 -> 0 | M27: =M9 -> 0
B28: Other income (expense) | C28: =SUM(-654,-2064,-3455,798,-337,381) -> -5331 | D28: =SUM(-1238,-1215,392,-628,299) -> -2390 | E28: =SUM(-409,-1043,3714,218,-188,919) -> 3211 | F28: =F10 -> 0 | G28: =G10 -> 0 | H28: =H10 -> 0 | I28: =I10 -> 0 | J28: =J10 -> 0 | K28: =K10 -> 0 | L28: =L10 -> 0 | M28: =M10 -> 0
B30: Interest income | C30: 2174 | D30: 3865 | E30: 4482 | F30: =IF(circ=1,Debt!F33,0) -> 0 | G30: =IF(circ=1,Debt!G33,0) -> 0 | H30: =IF(circ=1,Debt!H33,0) -> 0 | I30: =IF(circ=1,Debt!I33,0) -> 0 | J30: =IF(circ=1,Debt!J33,0) -> 0 | K30: =IF(circ=1,Debt!K33,0) -> 0 | L30: =IF(circ=1,Debt!L33,0) -> 0 | M30: =IF(circ=1,Debt!M33,0) -> 0
B31: Interest expense | C31: -357 | D31: -308 | E31: -268 | F31: =IF(circ=1,Debt!F21,0) -> 0 | G31: =IF(circ=1,Debt!G21,0) -> 0 | H31: =IF(circ=1,Debt!H21,0) -> 0 | I31: =IF(circ=1,Debt!I21,0) -> 0 | J31: =IF(circ=1,Debt!J21,0) -> 0 | K31: =IF(circ=1,Debt!K21,0) -> 0 | L31: =IF(circ=1,Debt!L21,0) -> 0 | M31: =IF(circ=1,Debt!M21,0) -> 0
A33: * | B33: Pretax Income | C33: =C21+SUM(C28:C31) -> 71328 | D33: =D21+SUM(D28:D31) -> 85460 | E33: =E21+SUM(E27:E31) -> 119815 | F33: =F21+SUM(F27:F28,F30:F31) -> 127615.27 | G33: =G21+SUM(G27:G28,G30:G31) -> 146990.55 | H33: =H21+SUM(H27:H28,H30:H31) -> 169246.43 | I33: =I21+SUM(I27:I28,I30:I31) -> 195745.96 | J33: =J21+SUM(J27:J28,J30:J31) -> 227436.19 | K33: =K21+SUM(K27:K28,K30:K31) -> 265502.78 | L33: =L21+SUM(L27:L28,L30:L31) -> 311434.93 | M33: =M21+SUM(M27:M28,M30:M31) -> 367108.68
B35: Tax expense | C35: 11356 | D35: 11922 | E35: 19697 | F35: =F33*F11 -> 23021.17 | G35: =G33*G11 -> 26516.377 | H35: =H33*H11 -> 30531.228 | I35: =I33*I11 -> 35311.614 | J35: =J33*J11 -> 41028.376 | K35: =K33*K11 -> 47895.403 | L35: =L33*L11 -> 56181.338 | M35: =M33*M11 -> 66224.61
A36: * | B36: Net income | C36: =C33-C35 -> 59972 | D36: =D33-D35 -> 73538 | E36: =E33-E35 -> 100118 | F36: =F33-F35 -> 104594.1 | G36: =G33-G35 -> 120474.18 | H36: =H33-H35 -> 138715.2 | I36: =I33-I35 -> 160434.35 | J36: =J33-J35 -> 186407.81 | ... M36: =M33-M35 -> 300884.07
B38: Dividends | C38: =C42*C36 -> 0 | D38: =D42*D36 -> 0 | E38: =E42*E36 -> 7363 | F38: =F36*F42 -> 8932.336 | G38: =G36*G42 -> 10288.495 | H38: =H36*H42 -> 11846.278 | I38: =I36*I42 -> 13701.093 | J38: =J36*J42 -> 15919.227 | K38: =K36*K42 -> 18583.67 | L38: =L36*L42 -> 21798.657 | M38: =M36*M42 -> 25695.499
A39: Shareholder information | C39: 44926 | D39: 45291 | E39: 45657 | F39: 46022 | G39: 46387 | H39: 46752 | I39: 47118 | J39: 47483 | K39: =2029+1 -> 2030 | L39: =K39+1 -> 2031 | M39: =L39+1 -> 2032
B40: Basic WASO | C40: =C36/C43 -> 13065.795 | D40: =D36/D43 -> 12592.123 | E40: =E36/E43 -> 12314.637 | F40: =Assumptions!F36 -> 12314.637 | G40: =Assumptions!G36 -> 12314.637 | H40: =Assumptions!H36 -> 12314.637 | I40: =Assumptions!I36 -> 12314.637 | J40: =Assumptions!J36 -> 12314.637 | K40: =Assumptions!K36 -> 12314.637 | L40: =Assumptions!L36 -> 12314.637 | M40: =Assumptions!M36 -> 12314.637
B41: Diluted WASO | C41: =C36/C44 -> 13151.754 | D41: =D36/D44 -> 12678.966 | E41: =E36/E44 -> 12452.488 | F41: =Assumptions!F37 -> 12452.488 | G41: =Assumptions!G37 -> 12452.488 | H41: =Assumptions!H37 -> 12452.488 | I41: =Assumptions!I37 -> 12452.488 | J41: =Assumptions!J37 -> 12452.488 | K41: =Assumptions!K37 -> 12452.488 | L41: =Assumptions!L37 -> 12452.488 | M41: =Assumptions!M37 -> 12452.488
B42: Dividend payout rate | C42: =C12 -> 0 | D42: =D12 -> 0 | E42: =E12 -> 0.073543219 | F42: =F12 -> 0.0854 | G42: =G12 -> 0.0854 | H42: =H12 -> 0.0854 | I42: =I12 -> 0.0854 | J42: =J12 -> 0.0854 | ... M42: =M12 -> 0.0854
B43: Basic earnings per share | C43: 4.59 | D43: 5.84 | E43: 8.13 | F43: =F36/F40 -> 8.4934779 | G43: =G36/G40 -> 9.7830066 | H43: =H36/H40 -> 11.264254 | I43: =I36/I40 -> 13.02794 | J43: =J36/J40 -> 15.137094 | K43: =K36/K40 -> 17.670628 | L43: =L36/L40 -> 20.727658 | M43: =M36/M40 -> 24.433044
A44: * | B44: Diluted earnings per share | C44: 4.56 | D44: 5.8 | E44: 8.04 | F44: =F36/F41 -> 8.3994541 | G44: =G36/G41 -> 9.6747077 | H44: =H36/H41 -> 11.139557 | I44: =I36/I41 -> 12.883719 | J44: =J36/J41 -> 14.969524 | K44: =K36/K41 -> 17.475013 | L44: =L36/L41 -> 20.498201 | M44: =M36/M41 -> 24.162567

Sheet BalSheet
A1: =CoName -> Alphabet Inc. | C1: Hist. | D1: Hist. | E1: Hist. | F1: Proj. | G1: Proj. | H1: Proj. | I1: Proj. | J1: Proj. | K1: Proj. | L1: Proj. | M1: Proj.
A2: Assumptions | C2: 44926 | D2: 45291 | E2: 45657 | F2: 46022 | G2: 46387 | H2: 46752 | I2: 47118 | J2: 47483 | K2: =2030 -> 2030 | L2: =K2+1 -> 2031 | M2: =L2+1 -> 2032
B4: Operating Cash % of sales | F4: =Assumptions!F40 -> 0.067042266 | G4: =F4 -> 0.067042266 | H4: =G4 -> 0.067042266 | I4: =H4 -> 0.067042266 | J4: =I4 -> 0.067042266 | K4: =J4 -> 0.067042266 | L4: =K4 -> 0.067042266 | M4: =L4 -> 0.067042266
B5: Accounts receivable % of sales | F5: =Assumptions!F41 -> 0.14953517 | G5: =Assumptions!G41 -> 0.14953517 | H5: =Assumptions!H41 -> 0.14953517 | I5: =Assumptions!I41 -> 0.14953517 | J5: =Assumptions!J41 -> 0.14953517 | K5: =Assumptions!K41 -> 0.14953517 | L5: =Assumptions!L41 -> 0.14953517 | M5: =Assumptions!M41 -> 0.14953517
B6: Inventories % of COGS | F6: =Assumptions!F42 -> 0 | G6: =Assumptions!G42 -> 0 | H6: =Assumptions!H42 -> 0 | I6: =Assumptions!I42 -> 0 | J6: =Assumptions!J42 -> 0 | K6: =Assumptions!K42 -> 0 | L6: =Assumptions!L42 -> 0 | M6: =Assumptions!M42 -> 0
B7: Other current assets % of sales | F7: =Assumptions!F43 -> 0.044894834 | G7: =Assumptions!G43 -> 0.044894834 | H7: =Assumptions!H43 -> 0.044894834 | I7: =Assumptions!I43 -> 0.044894834 | J7: =Assumptions!J43 -> 0.044894834 | K7: =Assumptions!K43 -> 0.044894834 | L7: =Assumptions!L43 -> 0.044894834 | M7: =Assumptions!M43 -> 0.044894834
B9: Other long-term assets % of sales | F9: =Assumptions!F46 -> 0.13039901 | G9: =Assumptions!G46 -> 0.13039901 | H9: =Assumptions!H46 -> 0.13039901 | I9: =Assumptions!I46 -> 0.13039901 | J9: =Assumptions!J46 -> 0.13039901 | K9: =Assumptions!K46 -> 0.13039901 | L9: =Assumptions!L46 -> 0.13039901 | M9: =Assumptions!M46 -> 0.13039901
B10: Investment in unconsolidated entities $ balance | F10: =Assumptions!F45 -> 37982 | G10: =Assumptions!G45 -> 37982 | H10: =Assumptions!H45 -> 37982 | I10: =Assumptions!I45 -> 37982 | J10: =Assumptions!J45 -> 37982 | K10: =Assumptions!K45 -> 37982 | L10: =Assumptions!L45 -> 37982 | M10: =Assumptions!M45 -> 37982
B12: Accounts payable/Accural % of COGS | F12: =Assumptions!F49 -> 0.57472694 | G12: =Assumptions!G49 -> 0.57472694 | H12: =Assumptions!H49 -> 0.57472694 | I12: =Assumptions!I49 -> 0.57472694 | J12: =Assumptions!J49 -> 0.57472694 | K12: =Assumptions!K49 -> 0.57472694 | L12: =Assumptions!L49 -> 0.57472694 | M12: =Assumptions!M49 -> 0.57472694
B13: Other current liabilities % of sales | F13: =Assumptions!F50 -> 0.014387831 | G13: =Assumptions!G50 -> 0.014387831 | H13: =Assumptions!H50 -> 0.014387831 | I13: =Assumptions!I50 -> 0.014387831 | J13: =Assumptions!J50 -> 0.014387831 | K13: =Assumptions!K50 -> 0.014387831 | L13: =Assumptions!L50 -> 0.014387831 | M13: =Assumptions!M50 -> 0.014387831
B14: Other long-term liabilities % of sales | F14: =Assumptions!F51 -> 0.071902016 | G14: =Assumptions!G51 -> 0.071902016 | H14: =Assumptions!H51 -> 0.071902016 | I14: =Assumptions!I51 -> 0.071902016 | J14: =Assumptions!J51 -> 0.071902016 | K14: =Assumptions!K51 -> 0.071902016 | L14: =Assumptions!L51 -> 0.071902016 | M14: =Assumptions!M51 -> 0.071902016
A15: Balance sheet | C15: =C2 -> 44926 | D15: =D2 -> 45291 | E15: =E2 -> 45657 | F15: =F2 -> 46022 | G15: =G2 -> 46387 | H15: =H2 -> 46752 | I15: =I2 -> 47118 | J15: =J2 -> 47483 | ... M15: =M2 -> 2032
B16: Operating Cash | C16: 21879 | D16: 24048 | E16: 23466 | F16: =IncState!F17*BalSheet!F4 -> 26937.203 | G16: =IncState!G17*BalSheet!G4 -> 30690.278 | H16: =IncState!H17*BalSheet!H4 -> 35337.1 | I16: =IncState!I17*BalSheet!I4 -> 40869.96 | J16: =IncState!J17*BalSheet!J4 -> 47486.588 | K16: =IncState!K17*BalSheet!K4 -> 55434.542 | L16: =IncState!L17*BalSheet!L4 -> 65024.753 | M16: =IncState!M17*BalSheet!M4 -> 76648.921
B17: Excess cash | C17: 91883 | D17: 86868 | E17: 72191 | F17: =MAX(CashFlow!F23,0) -> 99636.649 | G17: =MAX(CashFlow!G23,0) -> 144043.18 | H17: =MAX(CashFlow!H23,0) -> 205904.04 | I17: =MAX(CashFlow!I23,0) -> 288084.74 | J17: =MAX(CashFlow!J23,0) -> 394145.3 | K17: =MAX(CashFlow!K23,0) -> 528723.96 | L17: =MAX(CashFlow!L23,0) -> 697829.45 | M17: =MAX(CashFlow!M23,0) -> 909225.77
B18: Accounts receivable | C18: 40258 | D18: 47964 | E18: 52340 | F18: =IncState!F17*BalSheet!F5 -> 60082.384 | G18: =IncState!G17*BalSheet!G5 -> 68453.471 | H18: =IncState!H17*BalSheet!H5 -> 78818.027 | I18: =IncState!I17*BalSheet!I5 -> 91158.855 | J18: =IncState!J17*BalSheet!J5 -> 105916.99 | K18: =IncState!K17*BalSheet!K5 -> 123644.59 | L18: =IncState!L17*BalSheet!L5 -> 145035.18 | M18: =IncState!M17*BalSheet!M5 -> 170962.44
B19: Inventories | C19: 2670 | D19: 0 | E19: 0 | F19: =IncState!F18*BalSheet!F6 -> 0 | G19: =IncState!G18*BalSheet!G6 -> 0 | H19: =IncState!H18*BalSheet!H6 -> 0 | I19: =IncState!I18*BalSheet!I6 -> 0 | J19: =IncState!J18*BalSheet!J6 -> 0 | K19: =IncState!K18*BalSheet!K6 -> 0 | L19: =IncState!L18*BalSheet!L6 -> 0 | M19: =IncState!M18*BalSheet!M6 -> 0
B20: Other current assets | C20: 8105 | D20: 12650 | E20: 15714 | F20: =IncState!F17*BalSheet!F7 -> 18038.49 | G20: =IncState!G17*BalSheet!G7 -> 20551.736 | H20: =IncState!H17*BalSheet!H7 -> 23663.479 | I20: =IncState!I17*BalSheet!I7 -> 27368.556 | J20: =IncState!J17*BalSheet!J7 -> 31799.38 | K20: =IncState!K17*BalSheet!K7 -> 37121.725 | L20: =IncState!L17*BalSheet!L7 -> 43543.807 | M20: =IncState!M17*BalSheet!M7 -> 51327.927
B21: Total current assets | C21: =SUM(C16:C20) -> 164795 | D21: =SUM(D16:D20) -> 171530 | E21: =SUM(E16:E20) -> 163711 | F21: =SUM(F16:F20) -> 204694.73 | G21: =SUM(G16:G20) -> 263738.66 | H21: =SUM(H16:H20) -> 343722.65 | I21: =SUM(I16:I20) -> 447482.11 | J21: =SUM(J16:J20) -> 579348.25 | ... M21: =SUM(M16:M20) -> 1208165.1
B23: Property, plant & equipment, net | C23: 112668 | D23: 134345 | E23: 171036 | F23: =Calcs!F9 -> 235868.63 | G23: =Calcs!G9 -> 297989.55 | H23: =Calcs!H9 -> 358468.22 | I23: =Calcs!I9 -> 417627.73 | J23: =Calcs!J9 -> 475606.34 | K23: =Calcs!K9 -> 532304.28 | L23: =Calcs!L9 -> 587305.86 | M23: =Calcs!M9 -> 639767.69
B24: Intangible assets | C24: =28960+2084 -> 31044 | D24: 29198 | E24: 31885 | F24: =E24-IncState!F8 -> 31885 | G24: =F24-IncState!G8 -> 31885 | H24: =G24-IncState!H8 -> 31885 | I24: =H24-IncState!I8 -> 31885 | J24: =I24-IncState!J8 -> 31885 | K24: =J24-IncState!K8 -> 31885 | L24: =K24-IncState!L8 -> 31885 | M24: =L24-IncState!M8 -> 31885
B25: Investment in unconsolidated entities | C25: 30492 | D25: 31008 | E25: 37982 | F25: =F10 -> 37982 | G25: =G10 -> 37982 | H25: =H10 -> 37982 | I25: =I10 -> 37982 | J25: =J10 -> 37982 | K25: =K10 -> 37982 | L25: =L10 -> 37982 | M25: =M10 -> 37982
B26: Other assets | C26: =5261+14381+6623 -> 26265 | D26: =12169+14091+10051 -> 36311 | E26: =17180+13588+14874 -> 45642 | F26: =IncState!F17*BalSheet!F9 -> 52393.584 | G26: =IncState!G17*BalSheet!G9 -> 59693.415 | H26: =IncState!H17*BalSheet!H9 -> 68731.609 | I26: =IncState!I17*BalSheet!I9 -> 79493.169 | J26: =IncState!J17*BalSheet!J9 -> 92362.689 | K26: =IncState!K17*BalSheet!K9 -> 107821.67 | L26: =IncState!L17*BalSheet!L9 -> 126474.89 | M26: =IncState!M17*BalSheet!M9 -> 149084.21
B27: Total non-current assets | C27: =SUM(C23:C26) -> 200469 | D27: =SUM(D23:D26) -> 230862 | E27: =SUM(E23:E26) -> 286545 | F27: =SUM(F23:F26) -> 358129.21 | G27: =SUM(G23:G26) -> 427549.97 | H27: =SUM(H23:H26) -> 497066.82 | I27: =SUM(I23:I26) -> 566987.9 | J27: =SUM(J23:J26) -> 637836.03 | ... M27: =SUM(M23:M26) -> 858718.9
A29: * | B29: TOTAL ASSETS | C29: =SUM(C27,C21) -> 365264 | D29: =SUM(D27,D21) -> 402392 | E29: =SUM(E27,E21) -> 450256 | F29: =SUM(F27,F21) -> 562823.94 | G29: =SUM(G27,G21) -> 691288.63 | H29: =SUM(H27,H21) -> 840789.47 | I29: =SUM(I27,I21) -> 1014470 | J29: =SUM(J27,J21) -> 1217184.3 | ... M29: =SUM(M27,M21) -> 2066884
B31: Revolver/Short term debt | C31: 0 | D31: 0 | E31: 0 | F31: =MIN(CashFlow!F23,0) -> 0 | G31: =MIN(CashFlow!G23,0) -> 0 | H31: =MIN(CashFlow!H23,0) -> 0 | I31: =MIN(CashFlow!I23,0) -> 0 | J31: =MIN(CashFlow!J23,0) -> 0 | K31: =MIN(CashFlow!K23,0) -> 0 | L31: =MIN(CashFlow!L23,0) -> 0 | M31: =MIN(CashFlow!M23,0) -> 0
B32: Accounts payable/Accurals | C32: =69300-3908 -> 65392 | D32: =7493+15140+46168+8876 -> 77677 | E32: =7987+15069+51228+9802 -> 84086 | F32: =IncState!F18*BalSheet!F12 -> 96524.405 | G32: =IncState!G18*BalSheet!G12 -> 109972.84 | H32: =IncState!H18*BalSheet!H12 -> 126623.86 | I32: =IncState!I18*BalSheet!I12 -> 146449.82 | J32: =IncState!J18*BalSheet!J12 -> 170159.26 | K32: =IncState!K18*BalSheet!K12 -> 198639.26 | L32: =IncState!L18*BalSheet!L12 -> 233003.98 | M32: =IncState!M18*BalSheet!M12 -> 274657
B33: Other current liabilities | C33: 3908 | D33: 4137 | E33: 5036 | F33: =IncState!F17*BalSheet!F13 -> 5780.9493 | G33: =IncState!G17*BalSheet!G13 -> 6586.3905 | H33: =IncState!H17*BalSheet!H13 -> 7583.6375 | I33: =IncState!I17*BalSheet!I13 -> 8771.0354 | J33: =IncState!J17*BalSheet!J13 -> 10191.019 | K33: =IncState!K17*BalSheet!K13 -> 11896.717 | L33: =IncState!L17*BalSheet!L13 -> 13954.856 | M33: =IncState!M17*BalSheet!M13 -> 16449.5
B34: Total current liabilities | C34: =SUM(C31:C33) -> 69300 | D34: =SUM(D31:D33) -> 81814 | E34: =SUM(E31:E33) -> 89122 | F34: =SUM(F31:F33) -> 102305.35 | G34: =SUM(G31:G33) -> 116559.23 | H34: =SUM(H31:H33) -> 134207.49 | I34: =SUM(I31:I33) -> 155220.85 | J34: =SUM(J31:J33) -> 180350.28 | ... M34: =SUM(M31:M33) -> 291106.5
B36: Long-term debt, including current maturities | C36: 14701 | D36: 11870 | E36: 10883 | F36: =E36-Debt!F8 -> 10883 | G36: =F36-Debt!G8 -> 10883 | H36: =G36-Debt!H8 -> 10883 | I36: =H36-Debt!I8 -> 10883 | J36: =I36-Debt!J8 -> 10883 | K36: =J36-Debt!K8 -> 10883 | L36: =K36-Debt!L8 -> 10883 | M36: =L36-Debt!M8 -> 10883
B37: Other long-term liabilities | C37: =599+9258+514+12501+2247 -> 25119 | D37: =8474+12460+4395 -> 25329 | E37: =8782+11691+4694 -> 25167 | F37: =IncState!F17*BalSheet!F14 -> 28889.823 | G37: =IncState!G17*BalSheet!G14 -> 32914.95 | H37: =IncState!H17*BalSheet!H14 -> 37898.611 | I37: =IncState!I17*BalSheet!I14 -> 43832.535 | J37: =IncState!J17*BalSheet!J14 -> 50928.789 | K37: =IncState!K17*BalSheet!K14 -> 59452.873 | L37: =IncState!L17*BalSheet!L14 -> 69738.258 | M37: =IncState!M17*BalSheet!M14 -> 82205.037
B38: Total non-current liabilities | C38: =SUM(C36:C37) -> 39820 | D38: =SUM(D36:D37) -> 37199 | E38: =SUM(E36:E37) -> 36050 | F38: =SUM(F36:F37) -> 39772.823 | G38: =SUM(G36:G37) -> 43797.95 | H38: =SUM(H36:H37) -> 48781.611 | I38: =SUM(I36:I37) -> 54715.535 | J38: =SUM(J36:J37) -> 61811.789 | ... M38: =SUM(M36:M37) -> 93088.037
B40: Equity | C40: 256144 | D40: 283379 | E40: 325084 | F40: =Calcs!F18 -> 420745.76 | G40: =Calcs!G18 -> 530931.44 | H40: =Calcs!H18 -> 657800.37 | I40: =Calcs!I18 -> 804533.62 | J40: =Calcs!J18 -> 975022.21 | K40: =Calcs!K18 -> 1174045.9 | L40: =Calcs!L18 -> 1407500.8 | M40: =Calcs!M18 -> 1682689.4
A41: * | B41: TOTAL LIABILITIES & EQUITY | C41: =SUM(C40,C38,C34) -> 365264 | D41: =SUM(D40,D38,D34) -> 402392 | E41: =SUM(E40,E38,E34) -> 450256 | F41: =SUM(F40,F38,F34) -> 562823.94 | G41: =SUM(G40,G38,G34) -> 691288.63 | H41: =SUM(H40,H38,H34) -> 840789.47 | I41: =SUM(I40,I38,I34) -> 1014470 | J41: =SUM(J40,J38,J34) -> 1217184.3 | ... M41: =SUM(M40,M38,M34) -> 2066884
A43: * | B43: Balance check | C43: =C41-C29 -> 0 | D43: =D41-D29 -> 0 | E43: =E41-E29 -> 0 | F43: =F41-F29 -> 0 | G43: =G41-G29 -> 0 | H43: =H41-H29 -> 0 | I43: =I41-I29 -> 0 | J43: =J41-J29 -> 0 | ... M43: =M41-M29 -> 0

Sheet CashFlow
A1: =CoName -> Alphabet Inc. | C1: Hist. | D1: Hist. | E1: Hist. | F1: Proj. | G1: Proj. | H1: Proj. | I1: Proj. | J1: Proj. | K1: Proj. | L1: Proj. | M1: Proj.
A2: Cash flow statement | C2: 2022 | D2: =C2+1 -> 2023 | E2: =D2+1 -> 2024 | F2: =E2+1 -> 2025 | G2: =F2+1 -> 2026 | H2: =G2+1 -> 2027 | I2: =H2+1 -> 2028 | J2: =I2+1 -> 2029 | K2: =J2+1 -> 2030 | ... M2: =L2+1 -> 2032
B3: Net Income | F3: =IncState!F36 -> 104594.1 | G3: =IncState!G36 -> 120474.18 | H3: =IncState!H36 -> 138715.2 | I3: =IncState!I36 -> 160434.35 | J3: =IncState!J36 -> 186407.81 | K3: =IncState!K36 -> 217607.38 | L3: =IncState!L36 -> 255253.59 | M3: =IncState!M36 -> 300884.07
A4: + | B4: Depreciation | F4: =IncState!F23 -> 20347.771 | G4: =IncState!G23 -> 28060.765 | H4: =IncState!H23 -> 35451.152 | I4: =IncState!I23 -> 42646.164 | J4: =IncState!J23 -> 49684.239 | K4: =IncState!K23 -> 56581.825 | L4: =IncState!L23 -> 63327.053 | M4: =IncState!M23 -> 69870.468
A5: - | B5: Amortization | F5: =IncState!F8 -> 0 | G5: =IncState!G8 -> 0 | H5: =IncState!H8 -> 0 | I5: =IncState!I8 -> 0 | J5: =IncState!J8 -> 0 | K5: =IncState!K8 -> 0 | L5: =IncState!L8 -> 0 | M5: =IncState!M8 -> 0
B6: (inc) / dec in OWC | F6: =Calcs!F29 -> -354.72367 | G6: =Calcs!G29 -> -383.52821 | H6: =Calcs!H29 -> -474.86063 | I6: =Calcs!I29 -> -565.40514 | J6: =Calcs!J29 -> -676.15594 | K6: =Calcs!K29 -> -812.20465 | L6: =Calcs!L29 -> -980.0275 | M6: =Calcs!M29 -> -1187.8784
B7: (inc) / dec in Other LT assets | F7: =BalSheet!E26-BalSheet!F26 -> -6751.5837 | G7: =BalSheet!F26-BalSheet!G26 -> -7299.8309 | H7: =BalSheet!G26-BalSheet!H26 -> -9038.1939 | I7: =BalSheet!H26-BalSheet!I26 -> -10761.56 | J7: =BalSheet!I26-BalSheet!J26 -> -12869.52 | K7: =BalSheet!J26-BalSheet!K26 -> -15458.984 | L7: =BalSheet!K26-BalSheet!L26 -> -18653.217 | M7: =BalSheet!L26-BalSheet!M26 -> -22609.318
B8: inc / (dec) in Other LT liabilities | F8: =BalSheet!F37-BalSheet!E37 -> 3722.8235 | G8: =BalSheet!G37-BalSheet!F37 -> 4025.1269 | H8: =BalSheet!H37-BalSheet!G37 -> 4983.6603 | I8: =BalSheet!I37-BalSheet!H37 -> 5933.9246 | J8: =BalSheet!J37-BalSheet!I37 -> 7096.2538 | K8: =BalSheet!K37-BalSheet!J37 -> 8524.0844 | L8: =BalSheet!L37-BalSheet!K37 -> 10285.385 | M8: =BalSheet!M37-BalSheet!L37 -> 12466.779
B9: Operating Cash Flow | F9: =SUM(F3:F8) -> 121558.39 | G9: =SUM(G3:G8) -> 144876.71 | H9: =SUM(H3:H8) -> 169636.96 | I9: =SUM(I3:I8) -> 197687.47 | J9: =SUM(J3:J8) -> 229642.63 | K9: =SUM(K3:K8) -> 266442.1 | L9: =SUM(L3:L8) -> 309232.78 | M9: =SUM(M3:M8) -> 359424.12
B11: Capex | F11: =-Calcs!F7 -> -85180.401 | G11: =-Calcs!G7 -> -90181.688 | H11: =-Calcs!H7 -> -95929.815 | I11: =-Calcs!I7 -> -101805.68 | J11: =-Calcs!J7 -> -107662.85 | K11: =-Calcs!K7 -> -113279.77 | L11: =-Calcs!L7 -> -118328.64 | M11: =-Calcs!M7 -> -122332.3
B12: Investing Cash Flow | F12: =F11 -> -85180.401 | G12: =G11 -> -90181.688 | H12: =H11 -> -95929.815 | I12: =I11 -> -101805.68 | J12: =J11 -> -107662.85 | K12: =K11 -> -113279.77 | L12: =L11 -> -118328.64 | M12: =M11 -> -122332.3
B14: Dividends Paid | F14: =-IncState!F38 -> -8932.336 | G14: =-IncState!G38 -> -10288.495 | H14: =-IncState!H38 -> -11846.278 | I14: =-IncState!I38 -> -13701.093 | J14: =-IncState!J38 -> -15919.227 | K14: =-IncState!K38 -> -18583.67 | L14: =-IncState!L38 -> -21798.657 | M14: =-IncState!M38 -> -25695.499
B15: Share issuance / (repurchases) | F15: =Calcs!F12 -> 0 | G15: =Calcs!G12 -> 0 | H15: =Calcs!H12 -> 0 | I15: =Calcs!I12 -> 0 | J15: =Calcs!J12 -> 0 | K15: =Calcs!K12 -> 0 | L15: =Calcs!L12 -> 0 | M15: =Calcs!M12 -> 0
B16: Issuance / (repayment) of LT debt | F16: =Debt!F7-Debt!F8 -> 0 | G16: =Debt!G7-Debt!G8 -> 0 | H16: =Debt!H7-Debt!H8 -> 0 | I16: =Debt!I7-Debt!I8 -> 0 | J16: =Debt!J7-Debt!J8 -> 0 | K16: =Debt!K7-Debt!K8 -> 0 | L16: =Debt!L7-Debt!L8 -> 0 | M16: =Debt!M7-Debt!M8 -> 0
B17: Financing Cash flow | F17: =SUM(F14:F16) -> -8932.336 | G17: =SUM(G14:G16) -> -10288.495 | H17: =SUM(H14:H16) -> -11846.278 | I17: =SUM(I14:I16) -> -13701.093 | J17: =SUM(J14:J16) -> -15919.227 | K17: =SUM(K14:K16) -> -18583.67 | L17: =SUM(L14:L16) -> -21798.657 | M17: =SUM(M14:M16) -> -25695.499
B19: Net changes in Cash | F19: =SUM(F17,F12,F9) -> 27445.649 | G19: =SUM(G17,G12,G9) -> 44406.527 | H19: =SUM(H17,H12,H9) -> 61860.865 | I19: =SUM(I17,I12,I9) -> 82180.702 | J19: =SUM(J17,J12,J9) -> 106060.55 | K19: =SUM(K17,K12,K9) -> 134578.66 | L19: =SUM(L17,L12,L9) -> 169105.49 | M19: =SUM(M17,M12,M9) -> 211396.32
B21: Beginning balance | F21: =E23 -> 72191 | G21: =F23 -> 99636.649 | H21: =G23 -> 144043.18 | I21: =H23 -> 205904.04 | J21: =I23 -> 288084.74 | K21: =J23 -> 394145.3 | L21: =K23 -> 528723.96 | M21: =L23 -> 697829.45
B22: Changes in Balance | F22: =F19 -> 27445.649 | G22: =G19 -> 44406.527 | H22: =H19 -> 61860.865 | I22: =I19 -> 82180.702 | J22: =J19 -> 106060.55 | K22: =K19 -> 134578.66 | L22: =L19 -> 169105.49 | M22: =M19 -> 211396.32
B23: Ending Balance | E23: =BalSheet!E17 -> 72191 | F23: =SUM(F21:F22) -> 99636.649 | G23: =SUM(G21:G22) -> 144043.18 | H23: =SUM(H21:H22) -> 205904.04 | I23: =SUM(I21:I22) -> 288084.74 | J23: =SUM(J21:J22) -> 394145.3 | K23: =SUM(K21:K22) -> 528723.96 | L23: =SUM(L21:L22) -> 697829.45 | M23: =SUM(M21:M22) -> 909225.77

Sheet Free Cash Flow
A1: =CoName -> Alphabet Inc. | C1: Hist. | D1: Hist. | E1: Hist. | F1: Proj. | G1: Proj. | H1: Proj. | I1: Proj. | J1: Proj. | K1: Proj. | L1: Proj. | M1: Proj.
A2: Free Cash Flows | C2: 2022 | D2: =C2+1 -> 2023 | E2: =D2+1 -> 2024 | F2: =E2+1 -> 2025 | G2: =F2+1 -> 2026 | H2: =G2+1 -> 2027 | I2: =H2+1 -> 2028 | J2: =I2+1 -> 2029 | K2: =J2+1 -> 2030 | ... M2: =L2+1 -> 2032
A3: * | B3: Sales | F3: =IncState!F17 -> 401794.34 | G3: =IncState!G17 -> 457775.07 | H3: =IncState!H17 -> 527086.9 | I3: =IncState!I17 -> 609614.83 | J3: =IncState!J17 -> 708308.22 | K3: =IncState!K17 -> 826859.61 | L3: =IncState!L17 -> 969906.85 | M3: =IncState!M17 -> 1143292.5
B4: EBIT | F4: =IncState!F21 -> 129015.27 | G4: =IncState!G21 -> 146990.55 | H4: =IncState!H21 -> 169246.43 | I4: =IncState!I21 -> 195745.96 | J4: =IncState!J21 -> 227436.19 | K4: =IncState!K21 -> 265502.78 | L4: =IncState!L21 -> 311434.93 | M4: =IncState!M21 -> 367108.68
B5: Effective Tax Rate | F5: =Assumptions!F16 -> 0.18039511 | G5: =Assumptions!G16 -> 0.18039511 | H5: =Assumptions!H16 -> 0.18039511 | I5: =Assumptions!I16 -> 0.18039511 | J5: =Assumptions!J16 -> 0.18039511 | K5: =Assumptions!K16 -> 0.18039511 | L5: =Assumptions!L16 -> 0.18039511 | M5: =Assumptions!M16 -> 0.18039511
A7: * | B7: NOPAT | F7: =F4*(1-F5) -> 105741.54 | G7: =G4*(1-G5) -> 120474.18 | H7: =H4*(1-H5) -> 138715.2 | I7: =I4*(1-I5) -> 160434.35 | J7: =J4*(1-J5) -> 186407.81 | K7: =K4*(1-K5) -> 217607.38 | L7: =L4*(1-L5) -> 255253.59 | M7: =M4*(1-M5) -> 300884.07
B8: Depreciation | F8: =CashFlow!F4 -> 20347.771 | G8: =CashFlow!G4 -> 28060.765 | H8: =CashFlow!H4 -> 35451.152 | I8: =CashFlow!I4 -> 42646.164 | J8: =CashFlow!J4 -> 49684.239 | K8: =CashFlow!K4 -> 56581.825 | L8: =CashFlow!L4 -> 63327.053 | M8: =CashFlow!M4 -> 69870.468
B9: Amortization | F9: =CashFlow!F5 -> 0 | G9: =CashFlow!G5 -> 0 | H9: =CashFlow!H5 -> 0 | I9: =CashFlow!I5 -> 0 | J9: =CashFlow!J5 -> 0 | K9: =CashFlow!K5 -> 0 | L9: =CashFlow!L5 -> 0 | M9: =CashFlow!M5 -> 0
B10: (inc) / dec in OWC | F10: =CashFlow!F6 -> -354.72367 | G10: =CashFlow!G6 -> -383.52821 | H10: =CashFlow!H6 -> -474.86063 | I10: =CashFlow!I6 -> -565.40514 | J10: =CashFlow!J6 -> -676.15594 | K10: =CashFlow!K6 -> -812.20465 | L10: =CashFlow!L6 -> -980.0275 | M10: =CashFlow!M6 -> -1187.8784
B11: (inc) / dec in other long-term assets | F11: =CashFlow!F7 -> -6751.5837 | G11: =CashFlow!G7 -> -7299.8309 | H11: =CashFlow!H7 -> -9038.1939 | I11: =CashFlow!I7 -> -10761.56 | J11: =CashFlow!J7 -> -12869.52 | K11: =CashFlow!K7 -> -15458.984 | L11: =CashFlow!L7 -> -18653.217 | M11: =CashFlow!M7 -> -22609.318
B12: inc / (dec) other long-term liabilities | F12: =CashFlow!F8 -> 3722.8235 | G12: =CashFlow!G8 -> 4025.1269 | H12: =CashFlow!H8 -> 4983.6603 | I12: =CashFlow!I8 -> 5933.9246 | J12: =CashFlow!J8 -> 7096.2538 | K12: =CashFlow!K8 -> 8524.0844 | L12: =CashFlow!L8 -> 10285.385 | M12: =CashFlow!M8 -> 12466.779
B13: (Capex) | F13: =CashFlow!F11 -> -85180.401 | G13: =CashFlow!G11 -> -90181.688 | H13: =CashFlow!H11 -> -95929.815 | I13: =CashFlow!I11 -> -101805.68 | J13: =CashFlow!J11 -> -107662.85 | K13: =CashFlow!K11 -> -113279.77 | L13: =CashFlow!L11 -> -118328.64 | M13: =CashFlow!M11 -> -122332.3
A15: * | B15: Free Cash Flow | F15: =SUM(F7:F13) -> 37525.432 | G15: =SUM(G7:G13) -> 54695.021 | H15: =SUM(H7:H13) -> 73707.143 | I15: =SUM(I7:I13) -> 95881.796 | J15: =SUM(J7:J13) -> 121979.78 | K15: =SUM(K7:K13) -> 153162.33 | L15: =SUM(L7:L13) -> 190904.15 | M15: =SUM(M7:M13) -> 237091.82

Sheet WACC
A1: =CoName -> Alphabet Inc.
A3: * | B3: WACC | G3: Comp | H3: Levered beta | I3: Gross debt | J3: Market cap | K3: Debt/Mcap | L3: MTR | M3: Unlevered beta
B4: Tax Rate | E4: =Assumptions!E16 -> 0.16439511 | G4: MSFT | H4: 1.17 | I4: =2249+42868 -> 45117 | J4: =513.54*7400 -> 3800196 | K4: =I4/J4 -> 0.011872282 | L4: =E4 -> 0.16439511 | M4: =H4/((1+K4*(1-L4))) -> 1.158507
B5: Risk free rate | E5: 0.0414 | G5: AMZN | H5: 1.31 | I5: 54890 | J5: =219.3*10600 -> 2324580 | K5: =I5/J5 -> 0.023612868 | L5: =L4 -> 0.16439511 | M5: =H5/((1+K5*(1-L5))) -> 1.2846525
B6: Market risk Premium | E6: 0.05 | G6: META | H6: 1.24 | I6: =2016+28823 -> 30839 | J6: =718.88*2500 -> 1797200 | K6: =I6/J6 -> 0.01715947 | L6: =L5 -> 0.16439511 | M6: =H6/((1+K6*(1-L6))) -> 1.2224715
B7: Beta | E7: =M11 -> 1.2064202 | G7: AVGO | H7: 1.17 | I7: =1271+66295 -> 67566 | J7: =571.11*4700 -> 2684217 | K7: =I7/J7 -> 0.025171586 | L7: =L6 -> 0.16439511 | M7: =H7/((1+K7*(1-L7))) -> 1.1458978
B8: Cost of Equity | E8: =E5+E6*E7 -> 0.10172101
B9: % Equity | E9: =1-E10 -> 0.99648004 | G9: Industry beta (average) | M9: =AVERAGE(M4:M7) -> 1.2028822
B10: % Debt | E10: =BalSheet!E36/Inputs!F5 -> 0.0035199615
B11: Cost of debt | E11: 0.02 | G11: Re-levered beta | M11: =M9*(1+E10*(1-E4)) -> 1.2064202
B12: Post tax cost of debt | E12: =E11*(1-E4) -> 0.016712098
A13: * | B13: WACC | E13: =WACC!E8*WACC!E9+WACC!E12*WACC!E10 -> 0.10142178
B14: Long Term growth rate | E14: =0.03*0.46+0.038*0.54 -> 0.03432

Sheet DCF Model
A1: =CoName -> Alphabet Inc. | D1: Proj. | E1: Proj. | F1: Proj. | G1: Proj. | H1: Proj. | I1: Proj. | J1: Proj. | K1: Proj.
A2: Discount Model Year count | D2: 0.5 | E2: =D2+1 -> 1.5 | F2: =E2+1 -> 2.5 | G2: =F2+1 -> 3.5 | H2: =G2+1 -> 4.5 | I2: =H2+1 -> 5.5 | J2: =I2+1 -> 6.5 | K2: =J2+1 -> 7.5
B3: Discount Factor | D3: =1/(1+$C$28)^D2 -> 0.95285642 | E3: =1/(1+$C$28)^E2 -> 0.86513203 | F3: =1/(1+$C$28)^F2 -> 0.78548396 | G3: =1/(1+$C$28)^G2 -> 0.71316866 | H3: =1/(1+$C$28)^H2 -> 0.64751104 | I3: =1/(1+$C$28)^I2 -> 0.58789816 | J3: =1/(1+$C$28)^J2 -> 0.53377353 | K3: =1/(1+$C$28)^K2 -> 0.48463186
B4: Present value pf FCFs | D4: ='Free Cash Flow'!F15 -> 37525.432 | E4: ='Free Cash Flow'!G15 -> 54695.021 | F4: ='Free Cash Flow'!H15 -> 73707.143 | G4: ='Free Cash Flow'!I15 -> 95881.796 | H4: ='Free Cash Flow'!J15 -> 121979.78 | I4: ='Free Cash Flow'!K15 -> 153162.33 | J4: ='Free Cash Flow'!L15 -> 190904.15 | K4: ='Free Cash Flow'!M15 -> 237091.82
K5: =K4*(1+C29)/(C28-C29) -> 3654606.1
A6: Value Calculation | E6: Multiples Calculation
B7: Total PV of FCFs | C7: =SUM(D4:K4) -> 964947.47 | E7: Total PV of FCFs | G7: =C7 -> 964947.47
B8: PV of TV | C8: =K5*K3 -> 1771138.5 | E8: Multiple TV | G8: =(G10*IncState!M25)*K3 -> 1858767.5
B9: EV | C9: =C7+C8 -> 2736086 | E9: EV | G9: =SUM(G7:G8) -> 2823715
C10: =C9/IncState!M25 -> 6.2613652 | E10: Implied EBITDA multiple | G10: =K5*(1+C28)^0.5/(IncState!M25) -> 8.7771273
B12: Cash & Cash Equiv | C12: 95148 | E12: Cash & Cash Equiv | G12: =C12 -> 95148
B13: Debt & Claims | C13: 23607 | E13: Debt & Claims | G13: =C13 -> 23607
B14: NCI | C14: 0 | E14: NCI | G14: 0
B15: Equity Value | C15: =C9+C12-C13 -> 2807627 | E15: Equity Value | G15: =G9+G12-G13 -> 2895256
B17: Diluted S/O | C17: =IncState!E41 -> 12452.488 | E17: Diluted S/O | G17: =C17 -> 12452.488
A18: * | B18: Implied Share Price | C18: =(C9+C12-C13)/C17 -> 225.46716 | E18: Implied Share Price | G18: =G15/G17 -> 232.50422
A20: Sensitivity analysis
C22: Discount rate variance | E22: 0.005 | J22: Discount rate variance | L22: 0.005
C23: Implied growth rate variance | E23: 0.0025 | J23: TV multiple variance | L23: 1
A25: DCF tables
I26: Perpetuity | P26: Multiples
B28: WACC | C28: 0.1014 | I28: LTGR | P28: LTGR
B29: LT GR | C29: 0.0343 | H29: =H30 -> 0.0318 | I29: =I30 -> 0.0343 | J29: =J30 -> 0.0368 | O29: =O30 -> 0.0318 | P29: =P30 -> 0.0343 | Q29: =Q30 -> 0.0368
G30: =C18 -> 225.46716 | H30: =I30-$E$23 -> 0.0318 | I30: 0.0343 | J30: =I30+$E$23 -> 0.0368 | N30: =G10 -> 8.7771273 | O30: =P30-E23 -> 0.0318 | P30: 0.0343 | Q30: =P30+E23 -> 0.0368
F31: =G31 -> 0.1114 | G31: =G32+$E$22 -> 0.1114 | H31: 195.00281 | I31: 198.9065 | J31: 203.07183 | M31: =N31 -> 0.1114 | N31: =N32+$E$22 -> 0.1114 | O31: 7.4143573 | P31: 7.6733181 | Q31: 7.9496355
F32: =G32 -> 0.1064 | G32: =G33+$E$22 -> 0.1064 | H32: 206.59589 | I32: 211.18256 | J32: 216.09873 | M32: =N32 -> 0.1064 | N32: =N33+$E$22 -> 0.1064 | O32: 7.8934823 | P32: 8.18697 | Q32: 8.5015417
E33: WACC | F33: =G33 -> 0.1014 | G33: 0.1014 | H33: 220.02682 | I33: 225.46716 | J33: 231.32857 | L33: WACC | M33: =N33 -> 0.1014 | N33: 0.1014 | O33: 8.4414038 | P33: 8.7771273 | Q33: 9.1388356
F34: =G34 -> 0.0964 | G34: =G33-$E$22 -> 0.0964 | H34: 235.73051 | I34: 242.25396 | J34: 249.32469 | M34: =N34 -> 0.0964 | N34: =N33-$E$22 -> 0.0964 | O34: 9.0740962 | P34: 9.4622691 | Q34: 9.8830069
F35: =G35 -> 0.0914 | G35: =G34-$E$22 -> 0.0914 | H35: 254.28822 | I35: 262.20999 | J35: 270.8572 | M35: =N35 -> 0.0914 | N35: =N34-$E$22 -> 0.0914 | O35: 9.8128938 | P35: 10.267347 | Q35: 10.763417
I37: LTGR | P37: LTGR
H38: =H39 -> 0.0318 | I38: =I39 -> 0.0343 | J38: =J39 -> 0.0343 | O38: 7.8 | P38: 8.8 | Q38: 9.8
G39: =C10 -> 6.2613652 | H39: =I39-E23 -> 0.0318 | I39: 0.0343 | J39: =I39+D44 -> 0.0343 | N39: =G18 -> 232.50422 | O39: =P39-L23 -> 7.8 | P39: 8.8 | Q39: =P39+L23 -> 9.8
F40: =G40 -> 0.1114 | G40: =G41+$E$22 -> 0.1114 | H40: 5.39323 | I40: 5.5044725 | J40: 5.5044725 | M40: 0.1114 | N40: =N41+$E$22 -> 0.1114 | O40: 207.19251 | P40: 223.08444 | Q40: 238.97637
F41: =G41 -> 0.1064 | G41: =G42+$E$22 -> 0.1064 | H41: 5.7235953 | I41: 5.8543004 | J41: 5.8543004 | M41: 0.1064 | N41: =N42+$E$22 -> 0.1064 | O41: 211.4561 | P41: 227.89464 | Q41: 244.33318
E42: WACC | F42: =G42 -> 0.1014 | G42: 0.1014 | H42: 6.1063333 | I42: 6.2613652 | J42: 6.2613652 | L42: WACC | M42: 0.1014 | N42: 0.1014 | O42: 215.88665 | P42: 232.89321 | Q42: 249.89977
F43: =G43 -> 0.1014 | G43: =G42-D43 -> 0.1014 | H43: 6.1063333 | I43: 6.2613652 | J43: 6.2613652 | M43: 0.0964 | N43: =N42-$E$22 -> 0.0964 | O43: 220.49151 | P43: 238.08843 | Q43: 255.68536
F44: =G44 -> 0.1014 | G44: =G43-D44 -> 0.1014 | H44: 6.1063333 | I44: 6.2613652 | J44: 6.2613652 | M44: 0.0914 | N44: =N43-$E$22 -> 0.0914 | O44: 225.27837 | P44: 243.489 | Q44: 261.69963

Sheet COMPS
A1: =CoName -> Alphabet Inc.
A2: * | C2: Company Symbol | D2: Price 10/14/25 | E2: Enterprise Value | F2: LTM EV/EBITDA | G2: EV/EBITDA 2026E | H2: LTM EV/EBIT | I2: EV/EBIT 2026E | J2: LTM P/E Ratio | K2: P/E Ratio 2026E | L2: LTM EV/Sales | M2: EV/Sales 2026E | N2: Delta % Average
B3: Microsoft | C3: MSFT | D3: 514.54 | E3: 3844956.4 | F3: 22.85 | G3: 20.36 | H3: 29.74 | I3: 26.16 | J3: 37.54 | K3: 28.07 | L3: 13.55 | M3: 10.33
B4: Amazon | C4: AMZN | D4: 217.285 | E4: 2376169.1 | F4: 16.1 | G4: 11.64 | H4: 30.07 | I4: 24.33 | J4: 32.94 | K4: 23.81 | L4: 3.41 | M4: 2.95
B5: Meta | C5: META | D5: 711.517 | E5: 1789357.6 | F5: 18.51 | G5: 14.38 | H5: 22.73 | I5: 20.43 | J5: 25.63 | K5: 20.16 | L5: 10.01 | M5: 7.81
B6: Apple | C6: AAPL | D6: 247.55 | E6: 3642005.3 | F6: 25.7 | G6: 23.69 | H6: 27.97 | I6: 26.04 | J6: 34.12 | K6: 31.17 | L6: 9.12 | M6: 8.37
B7: Cisco | C7: CSCO | D7: 69.0951 | E7: 286679.1 | F7: 19.03 | G7: 12.22 | H7: 24.26 | I7: 13.71 | J7: 23.52 | K7: 15.79 | L7: 4.82 | M7: 4.34
A8: * | B8: Average | F8: =AVERAGE(F3:F7) -> 20.438 | G8: =AVERAGE(G3:G7) -> 16.458 | H8: =AVERAGE(H3:H7) -> 26.954 | I8: =AVERAGE(I3:I7) -> 22.134 | J8: =AVERAGE(J3:J7) -> 30.75 | K8: =AVERAGE(K3:K7) -> 23.8 | L8: =AVERAGE(L3:L7) -> 8.182 | M8: =AVERAGE(M3:M7) -> 6.76
A10: * | B10: Alphabet - Current Price | C10: GOOG | D10: =Inputs!C5 -> 253.3 | E10: =Inputs!F8 -> 3020254.2 | F10: 20.44 | G10: =E10/IncState!G25 -> 17.253536 | H10: 24.1 | I10: =E10/IncState!G21 -> 20.547267 | J10: 28.78 | K10: 21.3 | L10: 8.07 | M10: 7.87 | N10: =$E$10/F10 -> 147761.94 | O10: =$E$10/G10 -> 175051.32 | P10: =$E$10/H10 -> 125321.75 | Q10: =$E$10/I10 -> 146990.55
B11: Delta -> Average | F11: =(F10-F8)/$F$8 -> 9.7856933e-05 | G11: =(G10-G8)/G8 -> 0.048337316 | H11: =(H10-H8)/H8 -> -0.1058841 | I11: =(I10-I8)/I8 -> -0.071687588 | J11: =(J10-J8)/J8 -> -0.064065041 | K11: =(K10-K8)/K8 -> -0.10504202 | L11: =(L10-L8)/L8 -> -0.013688585 | M11: =(M10-M8)/M8 -> 0.16420118 | N11: =AVERAGE(F11:M11) -> -0.018466372
A13: * | B13: Alphabet - Upper Target | C13: GOOG | D13: 250 | E13: =D13*Inputs!$F$4-Inputs!$F$6+Inputs!$F$7 -> 2979974.2 | F13: =$E$13/N10 -> 20.167399 | G13: =$E$13/O10 -> 17.023432 | H13: =$E$13/P10 -> 23.778587 | I13: =$E$13/Q10 -> 20.273236 | J13: =$D$13/IncState!F44 -> 29.763839 | K13: =$D$13/IncState!G44 -> 25.840574 | L13: =$E$13/IncState!F17 -> 7.4166653 | M13: =$E$13/IncState!G17 -> 6.5096908
B14: Delta -> Average | F14: =(F13-F8)/F8 -> -0.013240074 | G14: =(G13-G8)/G8 -> 0.034356033 | H14: =(H13-H8)/H8 -> -0.11780859 | I14: =(I13-I8)/I8 -> -0.084068143 | J14: =(J13-J8)/J8 -> -0.032070278 | K14: =(K13-K8)/K8 -> 0.085738404 | L14: =(L13-L8)/L8 -> -0.093538832 | M14: =(M13-M8)/M8 -> -0.037027985 | N14: =AVERAGE(F14:M14) -> -0.032207433
A16: * | B16: Alphabet - Lower Target | C16: GOOG | D16: 230 | E16: =D16*Inputs!$F$4-Inputs!$F$6+Inputs!$F$7 -> 2735852.9 | F16: =$E$16/N10 -> 18.515274 | G16: =$E$16/O10 -> 15.628862 | H16: =$E$16/P10 -> 21.830632 | I16: =$E$16/Q10 -> 18.61244 | J16: =$D$16/IncState!F44 -> 27.382732 | K16: =$D$16/IncState!G44 -> 23.773328 | L16: =$E$16/IncState!F17 -> 6.8090878 | M16: =$E$16/IncState!G17 -> 5.9764132
B17: Delta -> Average | F17: =(F16-F10)/F10 -> -0.094164662 | G17: =(G16-G10)/G10 -> -0.094164662 | H17: =(H16-H10)/H10 -> -0.094164662 | I17: =(I16-I10)/I10 -> -0.094164662 | J17: =(J16-J10)/J10 -> -0.048549971 | K17: =(K16-K10)/K10 -> 0.11611869 | L17: =(L16-L10)/L10 -> -0.15624687 | M17: =(M16-M10)/M10 -> -0.24060824 | N17: =AVERAGE(F17:M17) -> -0.08824313
B19: Football field valuation data
C21: Low | E21: High | G21: LTM values (GOOG)
B22: LTM EV/EBITDA | C22: =MIN(F3:F7)*H23 -> 2303620.2 | D22: =E22-C22 -> 1373587.2 | E22: =MAX(F3:F7)*H23 -> 3677207.4 | G22: EV | H22: 2916321.9
B23: LTM EV/EBIT | C23: =H24*MIN(H3:H7) -> 2758740.1 | D23: =E23-C23 -> 890855.8 | E23: =MAX(H3:H7)*H24 -> 3649595.9 | G23: EBITDA | H23: 143082
B24: LTM P/E | C24: =MIN(J3:J7)*H25-Inputs!F6+Inputs!F7 -> 2397920.2 | D24: =E24-C24 -> 1472017.3 | E24: =MAX(J3:J7)*H25-Inputs!F6+Inputs!F7 -> 3869937.5 | G24: EBIT | H24: 121370
B25: LTM EV/REV | C25: =MIN(L3:L7)*H26 -> 1266470.6 | D25: =E25-C25 -> 2570081.1 | E25: =MAX(M3:M7)*H26 -> 3836551.7 | G25: Net income | H25: 104994.1
B26: 52-WK price | C26: =142.66*H27-Inputs!F6+Inputs!F7 -> 1668625.7 | D26: =E26-C26 -> 1391059.9 | E26: =256.7*H27-Inputs!F6+Inputs!F7 -> 3059685.6 | G26: Sales | H26: 371399
G27: Shares | H27: 12198
A28: Converted to share price | C28: Low | D28: Low - High | G28: EPS | H28: 8.53
B29: LTM EV/EBITDA | C29: =(C22+Inputs!$F$6-Inputs!$F$7)/Inputs!$F$4 -> 194.58868 | D29: =(D22+Inputs!$F$6-Inputs!$F$7)/Inputs!$F$4 -> 118.39432 | E29: =SUM(C29:D29) -> 312.98299
B30: LTM EV/EBIT | C30: =(C23+Inputs!$F$6-Inputs!$F$7)/Inputs!$F$4 -> 231.87507 | D30: =(D23+Inputs!$F$6-Inputs!$F$7)/Inputs!$F$4 -> 78.845815 | E30: =SUM(C30:D30) -> 310.72088
B31: LTM P/E | C31: =(C24+Inputs!$F$6-Inputs!$F$7)/Inputs!$F$4 -> 202.31435 | D31: =(D24+Inputs!$F$6-Inputs!$F$7)/Inputs!$F$4 -> 126.45835 | E31: =SUM(C31:D31) -> 328.7727
B32: LTM EV/REV | C32: =(C25+Inputs!$F$6-Inputs!$F$7)/Inputs!$F$4 -> 109.61863 | D32: =(D25+Inputs!$F$6-Inputs!$F$7)/Inputs!$F$4 -> 216.41889 | E32: =SUM(C32:D32) -> 326.03752
B33: 52-WK price | C33: =(C26+Inputs!$F$6-Inputs!$F$7)/Inputs!$F$4 -> 142.56579 | D33: =(D26+Inputs!$F$6-Inputs!$F$7)/Inputs!$F$4 -> 119.8258 | E33: =SUM(C33:D33) -> 262.39159
B34: IV Options Spread | C34: ='Volatility Analysis'!I3 -> 215.98947 | D34: =E34-C34 -> 74.621069 | E34: ='Volatility Analysis'!H3 -> 290.61053
B36: Valuation football field
G44: Football field Midpoint
G45: =(SUM(E29:E34,C29:C34)/12) -> 244.03902

Sheet Volatility Analysis
A1: =CoName -> Alphabet Inc.
A2: * | B2: Days from Expiration | C2: Expiration date | D2: Strike Price | E2: Call side Implied Vol | F2: Put Side Implied Vol | G2: Total implied move | H2: Upside deviation | I2: Downside deviation
B3: =C3-TODAY() -> 91 | C3: 46038 | D3: 245 | E3: 0.28 | F3: 0.29 | G3: =AVERAGE($E$8:$F$8)*SQRT(B3/365) -> 0.14729781 | H3: =$C$10*(1+G3) -> 290.61053 | I3: =$C$10*(1-G3) -> 215.98947
B4: =C4-TODAY() -> 154 | C4: 46101 | D4: 245 | E4: =E3+0.005 -> 0.285 | F4: =F3+0.005 -> 0.295 | G4: =AVERAGE($E$8:$F$8)*SQRT(B4/365) -> 0.19161784 | H4: =$C$10*(1+G4) -> 301.8368 | I4: =$C$10*(1-G4) -> 204.7632
B5: =C5-TODAY() -> 244 | C5: 46191 | D5: 245 | E5: =E4+0.005 -> 0.29 | F5: =F4+0.005 -> 0.3 | G5: =AVERAGE($E$8:$F$8)*SQRT(B5/365) -> 0.24119622 | H5: =$C$10*(1+G5) -> 314.395 | I5: =$C$10*(1-G5) -> 192.205
B6: =C6-TODAY() -> 336 | C6: 46283 | D6: 245 | E6: =E5+0.005 -> 0.295 | F6: =F5+0.005 -> 0.305 | G6: =AVERAGE($E$8:$F$8)*SQRT(B6/365) -> 0.28303831 | H6: =$C$10*(1+G6) -> 324.9936 | I6: =$C$10*(1-G6) -> 181.6064
B7: =C7-TODAY() -> 455 | C7: 46402 | D7: 245 | E7: =E6+0.005 -> 0.3 | F7: =F6+0.005 -> 0.31 | G7: =AVERAGE($E$8:$F$8)*SQRT(B7/365) -> 0.32936791 | H7: =$C$10*(1+G7) -> 336.72889 | I7: =$C$10*(1-G7) -> 169.87111
B8: Average | D8: =AVERAGE(D3:D7) -> 245 | E8: =AVERAGE(E3:E7) -> 0.29 | F8: =AVERAGE(F3:F7) -> 0.3 | G8: =AVERAGE(G3:G7) -> 0.23850362 | H8: =AVERAGE(H3:H7) -> 313.71297 | I8: =AVERAGE(I3:I7) -> 192.88703
B9: Ticker: GOOG
B10: Current Price | C10: =Inputs!C5 -> 253.3
A12: * | B12: Days from Expiration | C12: Expiration date | D12: Strike Price | E12: Call side Implied Vol | F12: Put Side Implied Vol | G12: Total implied move | H12: Upside deviation | I12: Downside deviation
B13: =C13-TODAY() -> 91 | C13: 46038 | D13: 6645 | E13: 0.1669 | F13: 0.1674 | G13: =AVERAGE($E$18:$F$18)*SQRT(B13/365) -> 0.088114047 | H13: =$C$20*(1+G13) -> 7229.767 | I13: =$C$20*(1-G13) -> 6058.853
B14: =C14-TODAY() -> 154 | C14: 46101 | D14: 6645 | E14: 0.174 | F14: 0.1749 | G14: =AVERAGE($E$18:$F$18)*SQRT(B14/365) -> 0.11462644 | H14: =$C$20*(1+G14) -> 7405.9236 | I14: =$C$20*(1-G14) -> 5882.6964
B15: =C15-TODAY() -> 244 | C15: 46191 | D15: 6645 | E15: 0.1757 | F15: 0.1762 | G15: =AVERAGE($E$18:$F$18)*SQRT(B15/365) -> 0.1442844 | H15: =$C$20*(1+G15) -> 7602.9803 | I15: =$C$20*(1-G15) -> 5685.6397
B16: =C16-TODAY() -> 336 | C16: 46283 | D16: 6645 | E16: 0.1803 | F16: 0.181 | G16: =AVERAGE($E$18:$F$18)*SQRT(B16/365) -> 0.16931448 | H16: =$C$20*(1+G16) -> 7769.2879 | I16: =$C$20*(1-G16) -> 5519.3321
B17: =C17-TODAY() -> 455 | C17: 46402 | D17: 6645 | E17: 0.1838 | F17: 0.1845 | G17: =AVERAGE($E$18:$F$18)*SQRT(B17/365) -> 0.197029 | H17: =$C$20*(1+G17) -> 7953.4318 | I17: =$C$20*(1-G17) -> 5335.1882
B18: Average | D18: =AVERAGE(D13:D17) -> 6645 | E18: =AVERAGE(E13:E17) -> 0.17614 | F18: =AVERAGE(F13:F17) -> 0.1768 | G18: =AVERAGE(G13:G17) -> 0.14267367 | H18: =AVERAGE(H13:H17) -> 7592.2781 | I18: =AVERAGE(I13:I17) -> 5696.3419
B19: Ticker: SPX
B20: Current Price | C20: 6644.31

Sheet SOTP analysis
A1: =CoName -> Alphabet Inc.
A2: SOTP analysis
A3: * | B3: Total Consolidated Business Segments | C3: Revenue 2025E | D3: EBIT 2025E | E3: D&A Allocation | F3: D&A Expense | G3: EBITDA 2025E | H3: EBIT% 2025E | I3: EBITDA% 2025E | J3: Multiples Calc 2025E | K3: Valuation Metric | L3: EV Implied Value
B4: =Revenues!B3 -> Google Search & Other | C4: =Revenues!S3 -> 222342.3 | D4: =C4*H4 -> 71393.617 | E4: =Capex!B3 -> 0.15 | F4: =E4*$F$11 -> 3052.1657 | G4: =D4+F4 -> 74445.783 | H4: =IncState!F21/IncState!F17 -> 0.32109777 | I4: =G4/C4 -> 0.3348251 | J4: =H16 -> 18.616512 | K4: EBITDA | L4: =G4*J4 -> 1385920.8
B5: =Revenues!B6 -> Youtube ads | C5: =Revenues!S6 -> 40426.784 | D5: =C5*H5 -> 12980.95 | E5: =Capex!B4 -> 0.1 | F5: =E5*$F$11 -> 2034.7771 | G5: =D5+F5 -> 15015.728 | H5: =H4 -> 0.32109777 | I5: =G5/C5 -> 0.37143017 | J5: =H22 -> 18.473152 | K5: EBITDA | L5: =J5*G5 -> 277387.82
B6: =Revenues!B9 -> Google Network | C6: =Revenues!S9 -> 30267.02 | D6: =C6*H6 -> 9718.6727 | E6: =Capex!B5 -> 0.05 | F6: =E6*$F$11 -> 1017.3886 | G6: =D6+F6 -> 10736.061 | H6: =H5 -> 0.32109777 | I6: =G6/C6 -> 0.35471154 | J6: =H28 -> 14.159716 | K6: EBITDA | L6: =J6*G6 -> 152019.58
D7: =C7*H7 -> 0 | F7: =E7*$F$11 -> 0 | G7: =D7+F7 -> 0 | H7: =H6 -> 0.32109777 | I7: =G7/C7 -> #DIV/0! | J7: =J6 -> 14.159716 | L7: =J7*C7 -> 0
B8: =Revenues!B16 -> Subscriptions, platforms, devices | C8: =Revenues!S16 -> 48328.8 | D8: =C8*H8 -> 15518.27 | E8: =Capex!B6 -> 0.07 | F8: =E8*$F$11 -> 1424.344 | G8: =D8+F8 -> 16942.614 | H8: =H7 -> 0.32109777 | I8: =G8/C8 -> 0.35056972 | J8: 7.7 | K8: Sales | L8: =J8*C8 -> 372131.76
B9: =Revenues!B19 -> Google Cloud | C9: =Revenues!S19 -> 58515.2 | D9: =C9*H9 -> 18789.1 | E9: =Capex!B7 -> 0.6 | F9: =E9*$F$11 -> 12208.663 | G9: =D9+F9 -> 30997.763 | H9: =H8 -> 0.32109777 | I9: =G9/C9 -> 0.52973865 | J9: =H35 -> 10.277958 | K9: Sales | L9: =J9*C9 -> 601416.77
B10: =Revenues!B22 -> Other bets | C10: =Revenues!S22 -> 1766.2385 | D10: =C10*H10 -> 567.13523 | E10: =Capex!B8 -> 0.03 | F10: =E10*$F$11 -> 610.43314 | G10: =D10+F10 -> 1177.5684 | H10: =H9 -> 0.32109777 | I10: =G10/C10 -> 0.66670974 | J10: =COMPS!M8 -> 6.76 | K10: Sales | L10: =J10*C10 -> 11939.772
A11: * | B11: Sum | C11: =SUM(C4:C10) -> 401646.34 | D11: =SUM(D4:D10) -> 128967.75 | E11: =SUM(E4:E10) -> 1 | F11: =IncState!F23 -> 20347.771 | G11: =SUM(G4:G10) -> 149315.52 | L11: =SUM(L4:L10) -> 2800816.5
L12: =Inputs!F6 -> 95148
L13: =Inputs!F7 -> 23607
J14: Equity value | L14: =L11+L12-L13 -> 2872357.5
B15: Beta calcs | E15: EV/EBITDA Calcs | J15: Implied SOTP share | L15: =L14/Inputs!F4 -> 235.32224
B16: ev/ebitda beta | C16: =(C20-C19)/(C18-C17) -> 0.40879275 | E16: Google Search & Other Multiples calc | H16: =F17+F18*(F19-F20) -> 18.616512
B17: Base CAGR * 100 | C17: =Revenues!AA26*100 -> 14.668132 | E17: Base multiple | F17: 20.4
B18: High CAGR * 100 | C18: =Revenues!AA19*100 -> 27.54018 | E18: Beta | F18: =C16 -> 0.40879275
B19: Low EV/EBITDA Multiple | C19: =COMPS!F8 -> 20.438 | E19: Real CAGR | F19: =Revenues!AA3*100 -> 10.637183
B20: Base EV/EBITDA Multiple | C20: =COMPS!F6 -> 25.7 | E20: Base CAGR | F20: =15%*100 -> 15
B22: ev/sale beta | C22: =(C26-C25)/(C24-C23) -> 0.27734514 | E22: Youtube ads multiples calc | H22: =F23+F24*(F25-F26) -> 18.473152
B23: Base CAGR * 100 | C23: =C17 -> 14.668132 | E23: Base multiple | F23: 20.4
B24: High CAGR * 100 | C24: =C18 -> 27.54018 | E24: Beta | F24: =C16 -> 0.40879275
B25: Low EV/Sales Multiple | C25: =COMPS!M8 -> 6.76 | E25: Real CAGR | F25: =Revenues!AA6*100 -> 10.286492
B26: Base EV/Sales Multiple | C26: =COMPS!M3 -> 10.33 | E26: Base CAGR | F26: =15%*100 -> 15
E28: Google Network multiples calc | H28: =F29+F30*(F31-F32) -> 14.159716
E29: Base multiple | F29: 20.4
E30: Beta | F30: =C16 -> 0.40879275
E31: Real CAGR | F31: =Revenues!AA9*100 -> -0.26515286
E32: Base CAGR | F32: =15%*100 -> 15
E34: EV/Sales Calcs
E35: Google cloud Multiples calc | H35: =F36+F37*(F38-F39) -> 10.277958
E36: Base multiple | F36: 6.8
E37: Beta | F37: =C22 -> 0.27734514
E38: Real CAGR | F38: =Revenues!AA19*100 -> 27.54018
E39: Base CAGR | F39: =15%*100 -> 15
E41: Subs/Platforms/Devices Calc | H41: =F42+F43*(F44-F45) -> 7.3902372
E42: Base multiple | F42: 6.8
E43: Beta | F43: =C22 -> 0.27734514
E44: Real CAGR | F44: =Revenues!AA16*100 -> 17.128169
E45: Base CAGR | F45: =15%*100 -> 15

Sheet Presentation
A1: =CoName -> Alphabet Inc.
A2: Presentation slide
A3: Football field + SOTP Comps analysis
F4: Football field Midpoint
F5: 242.73068
K7: Total Consolidated Business Segments | L7: Multiples 2025E | M7: Valuation Metric | N7: EV Implied Value
K8: ='SOTP analysis'!B4 -> Google Search & Other | L8: ='SOTP analysis'!J4 -> 18.616512 | M8: ='SOTP analysis'!K4 -> EBITDA | N8: ='SOTP analysis'!L4 -> 1385920.8
K9: ='SOTP analysis'!B5 -> Youtube ads | L9: ='SOTP analysis'!J5 -> 18.473152 | M9: ='SOTP analysis'!K5 -> EBITDA | N9: ='SOTP analysis'!L5 -> 277387.82
K10: ='SOTP analysis'!B6 -> Google Network | L10: ='SOTP analysis'!J6 -> 14.159716 | M10: ='SOTP analysis'!K6 -> EBITDA | N10: ='SOTP analysis'!L6 -> 152019.58
K11: Subs/Platform/Devices | L11: ='SOTP analysis'!J8 -> 7.7 | M11: ='SOTP analysis'!K8 -> Sales | N11: ='SOTP analysis'!L8 -> 372131.76
K12: ='SOTP analysis'!B9 -> Google Cloud | L12: ='SOTP analysis'!J9 -> 10.277958 | M12: ='SOTP analysis'!K9 -> Sales | N12: ='SOTP analysis'!L9 -> 601416.77
K13: ='SOTP analysis'!B10 -> Other bets | L13: ='SOTP analysis'!J10 -> 6.76 | M13: ='SOTP analysis'!K10 -> Sales | N13: ='SOTP analysis'!L10 -> 11939.772
L14: Total EV | N14: =SUM(N8:N13) -> 2800816.5
L15: Equity value | N15: ='SOTP analysis'!L14 -> 2872357.5
L16: Implied SOTP share | N16: ='SOTP analysis'!L15 -> 235.32224
A21: DCF Analysis (Sensitivity tables)
G23: Gordon Growth Terminal Calculation | N23: Implied Terminal Multiples Calculation
G25: LTGR | N25: LTGR
F26: 0.0318 | G26: 0.0343 | H26: 0.0368 | M26: 7.8 | N26: 8.8 | O26: 9.8
E27: 0.1114 | F27: 195.00281 | G27: 198.9065 | H27: 203.07183 | L27: 0.1114 | M27: 207.19251 | N27: 223.08444 | O27: 238.97637
E28: 0.1064 | F28: 206.59589 | G28: 211.18256 | H28: 216.09873 | L28: 0.1064 | M28: 211.4561 | N28: 227.89464 | O28: 244.33318
E29: WACC 10.14% | F29: 220.02682 | G29: 225.46716 | H29: 231.32857 | L29: WACC 10.14% | M29: 215.88665 | N29: 232.89321 | O29: 249.89977
E30: 0.0964 | F30: 235.73051 | G30: 242.25396 | H30: 249.32469 | L30: 0.0964 | M30: 220.49151 | N30: 238.08843 | O30: 255.68536
E31: 0.0914 | F31: 254.28822 | G31: 262.20999 | H31: 270.8572 | L31: 0.0914 | M31: 225.27837 | N31: 243.489 | O31: 261.69963
G33: LTGR | N33: LTGR
F34: 0.0318 | G34: 0.0343 | H34: 0.0343 | M34: 0.0318 | N34: 0.0343 | O34: 0.0368
E35: 0.1114 | F35: 5.39323 | G35: 5.5044725 | H35: 5.5044725 | L35: 0.1114 | M35: 7.4143573 | N35: 7.6733181 | O35: 7.9496355
E36: 0.1064 | F36: 5.7235953 | G36: 5.8543004 | H36: 5.8543004 | L36: 0.1064 | M36: 7.8934823 | N36: 8.18697 | O36: 8.5015417
E37: WACC 10.14% | F37: 6.1063333 | G37: 6.2613652 | H37: 6.2613652 | L37: WACC 10.14% | M37: 8.4414038 | N37: 8.7771273 | O37: 9.1388356
E38: 0.1014 | F38: 6.1063333 | G38: 6.2613652 | H38: 6.2613652 | L38: 0.0964 | M38: 9.0740962 | N38: 9.4622691 | O38: 9.8830069
E39: 0.1014 | F39: 6.1063333 | G39: 6.2613652 | H39: 6.2613652 | L39: 0.0914 | M39: 9.8128938 | N39: 10.267347 | O39: 10.763417
A41: Projection ranges
